{
    "('I-IA', 'I-IA')": {
        "Nx": 23,
        "Ny": 23,
        "Nxy": 23,
        "F": 1.0,
        "F_value": "1.00"
    },
    "('I-IA', 'I-IB')": {
        "Nx": 23,
        "Ny": 25,
        "Nxy": 21,
        "F": 0.875,
        "F_value": "0.88"
    },
    "('I-IA', 'I-IC')": {
        "Nx": 23,
        "Ny": 23,
        "Nxy": 17,
        "F": 0.7391304347826086,
        "F_value": "0.74"
    },
    "('I-IA', 'I-IE')": {
        "Nx": 23,
        "Ny": 25,
        "Nxy": 19,
        "F": 0.7916666666666666,
        "F_value": "0.79"
    },
    "('I-IA', 'I-IF')": {
        "Nx": 23,
        "Ny": 24,
        "Nxy": 19,
        "F": 0.8085106382978723,
        "F_value": "0.81"
    },
    "('I-IA', 'I-IIA')": {
        "Nx": 23,
        "Ny": 24,
        "Nxy": 16,
        "F": 0.6808510638297872,
        "F_value": "0.68"
    },
    "('I-IA', 'I-IIB')": {
        "Nx": 23,
        "Ny": 24,
        "Nxy": 17,
        "F": 0.723404255319149,
        "F_value": "0.72"
    },
    "('I-IA', 'I-IIIB')": {
        "Nx": 23,
        "Ny": 25,
        "Nxy": 18,
        "F": 0.75,
        "F_value": "0.75"
    },
    "('I-IA', 'I-IP')": {
        "Nx": 23,
        "Ny": 22,
        "Nxy": 16,
        "F": 0.7111111111111111,
        "F_value": "0.71"
    },
    "('I-IA', 'I-IVB')": {
        "Nx": 23,
        "Ny": 25,
        "Nxy": 18,
        "F": 0.75,
        "F_value": "0.75"
    },
    "('I-IA', 'I-VB')": {
        "Nx": 23,
        "Ny": 24,
        "Nxy": 20,
        "F": 0.851063829787234,
        "F_value": "0.85"
    },
    "('I-IA', 'I-VIB')": {
        "Nx": 23,
        "Ny": 24,
        "Nxy": 20,
        "F": 0.851063829787234,
        "F_value": "0.85"
    },
    "('I-IA', 'II-IA')": {
        "Nx": 23,
        "Ny": 24,
        "Nxy": 1,
        "F": 0.0425531914893617,
        "F_value": "0.04"
    },
    "('I-IA', 'IX-IB')": {
        "Nx": 23,
        "Ny": 22,
        "Nxy": 4,
        "F": 0.17777777777777778,
        "F_value": "0.18"
    },
    "('I-IA', 'IX-IH')": {
        "Nx": 23,
        "Ny": 20,
        "Nxy": 6,
        "F": 0.27906976744186046,
        "F_value": "0.28"
    },
    "('I-IA', 'V-IA')": {
        "Nx": 23,
        "Ny": 29,
        "Nxy": 4,
        "F": 0.15384615384615385,
        "F_value": "0.15"
    },
    "('I-IA', 'VII-IA')": {
        "Nx": 23,
        "Ny": 24,
        "Nxy": 5,
        "F": 0.2127659574468085,
        "F_value": "0.21"
    },
    "('I-IA', 'X-IA')": {
        "Nx": 23,
        "Ny": 19,
        "Nxy": 3,
        "F": 0.14285714285714285,
        "F_value": "0.14"
    },
    "('I-IA', 'X-IC')": {
        "Nx": 23,
        "Ny": 18,
        "Nxy": 4,
        "F": 0.1951219512195122,
        "F_value": "0.20"
    },
    "('I-IA', 'X-IF')": {
        "Nx": 23,
        "Ny": 19,
        "Nxy": 5,
        "F": 0.23809523809523808,
        "F_value": "0.24"
    },
    "('I-IA', 'XII-IA')": {
        "Nx": 23,
        "Ny": 22,
        "Nxy": 3,
        "F": 0.13333333333333333,
        "F_value": "0.13"
    },
    "('I-IA', 'XII-IB')": {
        "Nx": 23,
        "Ny": 23,
        "Nxy": 3,
        "F": 0.13043478260869565,
        "F_value": "0.13"
    },
    "('I-IA', 'XIII-IA')": {
        "Nx": 23,
        "Ny": 29,
        "Nxy": 6,
        "F": 0.23076923076923078,
        "F_value": "0.23"
    },
    "('I-IA', 'XIV-IA')": {
        "Nx": 23,
        "Ny": 23,
        "Nxy": 0,
        "F": 0.0,
        "F_value": "0.00"
    },
    "('I-IA', 'XIV-IC')": {
        "Nx": 23,
        "Ny": 23,
        "Nxy": 0,
        "F": 0.0,
        "F_value": "0.00"
    },
    "('I-IB', 'I-IA')": {
        "Nx": 25,
        "Ny": 23,
        "Nxy": 21,
        "F": 0.875,
        "F_value": "0.88"
    },
    "('I-IB', 'I-IB')": {
        "Nx": 25,
        "Ny": 25,
        "Nxy": 25,
        "F": 1.0,
        "F_value": "1.00"
    },
    "('I-IB', 'I-IC')": {
        "Nx": 25,
        "Ny": 23,
        "Nxy": 18,
        "F": 0.75,
        "F_value": "0.75"
    },
    "('I-IB', 'I-IE')": {
        "Nx": 25,
        "Ny": 25,
        "Nxy": 19,
        "F": 0.76,
        "F_value": "0.76"
    },
    "('I-IB', 'I-IF')": {
        "Nx": 25,
        "Ny": 24,
        "Nxy": 20,
        "F": 0.8163265306122449,
        "F_value": "0.82"
    },
    "('I-IB', 'I-IIA')": {
        "Nx": 25,
        "Ny": 24,
        "Nxy": 17,
        "F": 0.6938775510204082,
        "F_value": "0.69"
    },
    "('I-IB', 'I-IIB')": {
        "Nx": 25,
        "Ny": 24,
        "Nxy": 21,
        "F": 0.8571428571428571,
        "F_value": "0.86"
    },
    "('I-IB', 'I-IIIB')": {
        "Nx": 25,
        "Ny": 25,
        "Nxy": 22,
        "F": 0.88,
        "F_value": "0.88"
    },
    "('I-IB', 'I-IP')": {
        "Nx": 25,
        "Ny": 22,
        "Nxy": 16,
        "F": 0.6808510638297872,
        "F_value": "0.68"
    },
    "('I-IB', 'I-IVB')": {
        "Nx": 25,
        "Ny": 25,
        "Nxy": 19,
        "F": 0.76,
        "F_value": "0.76"
    },
    "('I-IB', 'I-VB')": {
        "Nx": 25,
        "Ny": 24,
        "Nxy": 23,
        "F": 0.9387755102040817,
        "F_value": "0.94"
    },
    "('I-IB', 'I-VIB')": {
        "Nx": 25,
        "Ny": 24,
        "Nxy": 23,
        "F": 0.9387755102040817,
        "F_value": "0.94"
    },
    "('I-IB', 'II-IA')": {
        "Nx": 25,
        "Ny": 24,
        "Nxy": 1,
        "F": 0.04081632653061224,
        "F_value": "0.04"
    },
    "('I-IB', 'IX-IB')": {
        "Nx": 25,
        "Ny": 22,
        "Nxy": 4,
        "F": 0.1702127659574468,
        "F_value": "0.17"
    },
    "('I-IB', 'IX-IH')": {
        "Nx": 25,
        "Ny": 20,
        "Nxy": 6,
        "F": 0.26666666666666666,
        "F_value": "0.27"
    },
    "('I-IB', 'V-IA')": {
        "Nx": 25,
        "Ny": 29,
        "Nxy": 4,
        "F": 0.14814814814814814,
        "F_value": "0.15"
    },
    "('I-IB', 'VII-IA')": {
        "Nx": 25,
        "Ny": 24,
        "Nxy": 5,
        "F": 0.20408163265306123,
        "F_value": "0.20"
    },
    "('I-IB', 'X-IA')": {
        "Nx": 25,
        "Ny": 19,
        "Nxy": 3,
        "F": 0.13636363636363635,
        "F_value": "0.14"
    },
    "('I-IB', 'X-IC')": {
        "Nx": 25,
        "Ny": 18,
        "Nxy": 4,
        "F": 0.18604651162790697,
        "F_value": "0.19"
    },
    "('I-IB', 'X-IF')": {
        "Nx": 25,
        "Ny": 19,
        "Nxy": 5,
        "F": 0.22727272727272727,
        "F_value": "0.23"
    },
    "('I-IB', 'XII-IA')": {
        "Nx": 25,
        "Ny": 22,
        "Nxy": 3,
        "F": 0.1276595744680851,
        "F_value": "0.13"
    },
    "('I-IB', 'XII-IB')": {
        "Nx": 25,
        "Ny": 23,
        "Nxy": 3,
        "F": 0.125,
        "F_value": "0.12"
    },
    "('I-IB', 'XIII-IA')": {
        "Nx": 25,
        "Ny": 29,
        "Nxy": 6,
        "F": 0.2222222222222222,
        "F_value": "0.22"
    },
    "('I-IB', 'XIV-IA')": {
        "Nx": 25,
        "Ny": 23,
        "Nxy": 0,
        "F": 0.0,
        "F_value": "0.00"
    },
    "('I-IB', 'XIV-IC')": {
        "Nx": 25,
        "Ny": 23,
        "Nxy": 0,
        "F": 0.0,
        "F_value": "0.00"
    },
    "('I-IC', 'I-IA')": {
        "Nx": 23,
        "Ny": 23,
        "Nxy": 17,
        "F": 0.7391304347826086,
        "F_value": "0.74"
    },
    "('I-IC', 'I-IB')": {
        "Nx": 23,
        "Ny": 25,
        "Nxy": 18,
        "F": 0.75,
        "F_value": "0.75"
    },
    "('I-IC', 'I-IC')": {
        "Nx": 23,
        "Ny": 23,
        "Nxy": 23,
        "F": 1.0,
        "F_value": "1.00"
    },
    "('I-IC', 'I-IE')": {
        "Nx": 23,
        "Ny": 25,
        "Nxy": 19,
        "F": 0.7916666666666666,
        "F_value": "0.79"
    },
    "('I-IC', 'I-IF')": {
        "Nx": 23,
        "Ny": 24,
        "Nxy": 19,
        "F": 0.8085106382978723,
        "F_value": "0.81"
    },
    "('I-IC', 'I-IIA')": {
        "Nx": 23,
        "Ny": 24,
        "Nxy": 17,
        "F": 0.723404255319149,
        "F_value": "0.72"
    },
    "('I-IC', 'I-IIB')": {
        "Nx": 23,
        "Ny": 24,
        "Nxy": 15,
        "F": 0.6382978723404256,
        "F_value": "0.64"
    },
    "('I-IC', 'I-IIIB')": {
        "Nx": 23,
        "Ny": 25,
        "Nxy": 16,
        "F": 0.6666666666666666,
        "F_value": "0.67"
    },
    "('I-IC', 'I-IP')": {
        "Nx": 23,
        "Ny": 22,
        "Nxy": 16,
        "F": 0.7111111111111111,
        "F_value": "0.71"
    },
    "('I-IC', 'I-IVB')": {
        "Nx": 23,
        "Ny": 25,
        "Nxy": 19,
        "F": 0.7916666666666666,
        "F_value": "0.79"
    },
    "('I-IC', 'I-VB')": {
        "Nx": 23,
        "Ny": 24,
        "Nxy": 17,
        "F": 0.723404255319149,
        "F_value": "0.72"
    },
    "('I-IC', 'I-VIB')": {
        "Nx": 23,
        "Ny": 24,
        "Nxy": 17,
        "F": 0.723404255319149,
        "F_value": "0.72"
    },
    "('I-IC', 'II-IA')": {
        "Nx": 23,
        "Ny": 24,
        "Nxy": 2,
        "F": 0.0851063829787234,
        "F_value": "0.09"
    },
    "('I-IC', 'IX-IB')": {
        "Nx": 23,
        "Ny": 22,
        "Nxy": 3,
        "F": 0.13333333333333333,
        "F_value": "0.13"
    },
    "('I-IC', 'IX-IH')": {
        "Nx": 23,
        "Ny": 20,
        "Nxy": 5,
        "F": 0.23255813953488372,
        "F_value": "0.23"
    },
    "('I-IC', 'V-IA')": {
        "Nx": 23,
        "Ny": 29,
        "Nxy": 3,
        "F": 0.11538461538461539,
        "F_value": "0.12"
    },
    "('I-IC', 'VII-IA')": {
        "Nx": 23,
        "Ny": 24,
        "Nxy": 4,
        "F": 0.1702127659574468,
        "F_value": "0.17"
    },
    "('I-IC', 'X-IA')": {
        "Nx": 23,
        "Ny": 19,
        "Nxy": 5,
        "F": 0.23809523809523808,
        "F_value": "0.24"
    },
    "('I-IC', 'X-IC')": {
        "Nx": 23,
        "Ny": 18,
        "Nxy": 7,
        "F": 0.34146341463414637,
        "F_value": "0.34"
    },
    "('I-IC', 'X-IF')": {
        "Nx": 23,
        "Ny": 19,
        "Nxy": 7,
        "F": 0.3333333333333333,
        "F_value": "0.33"
    },
    "('I-IC', 'XII-IA')": {
        "Nx": 23,
        "Ny": 22,
        "Nxy": 3,
        "F": 0.13333333333333333,
        "F_value": "0.13"
    },
    "('I-IC', 'XII-IB')": {
        "Nx": 23,
        "Ny": 23,
        "Nxy": 3,
        "F": 0.13043478260869565,
        "F_value": "0.13"
    },
    "('I-IC', 'XIII-IA')": {
        "Nx": 23,
        "Ny": 29,
        "Nxy": 7,
        "F": 0.2692307692307692,
        "F_value": "0.27"
    },
    "('I-IC', 'XIV-IA')": {
        "Nx": 23,
        "Ny": 23,
        "Nxy": 1,
        "F": 0.043478260869565216,
        "F_value": "0.04"
    },
    "('I-IC', 'XIV-IC')": {
        "Nx": 23,
        "Ny": 23,
        "Nxy": 1,
        "F": 0.043478260869565216,
        "F_value": "0.04"
    },
    "('I-IE', 'I-IA')": {
        "Nx": 25,
        "Ny": 23,
        "Nxy": 19,
        "F": 0.7916666666666666,
        "F_value": "0.79"
    },
    "('I-IE', 'I-IB')": {
        "Nx": 25,
        "Ny": 25,
        "Nxy": 19,
        "F": 0.76,
        "F_value": "0.76"
    },
    "('I-IE', 'I-IC')": {
        "Nx": 25,
        "Ny": 23,
        "Nxy": 19,
        "F": 0.7916666666666666,
        "F_value": "0.79"
    },
    "('I-IE', 'I-IE')": {
        "Nx": 25,
        "Ny": 25,
        "Nxy": 25,
        "F": 1.0,
        "F_value": "1.00"
    },
    "('I-IE', 'I-IF')": {
        "Nx": 25,
        "Ny": 24,
        "Nxy": 20,
        "F": 0.8163265306122449,
        "F_value": "0.82"
    },
    "('I-IE', 'I-IIA')": {
        "Nx": 25,
        "Ny": 24,
        "Nxy": 15,
        "F": 0.6122448979591837,
        "F_value": "0.61"
    },
    "('I-IE', 'I-IIB')": {
        "Nx": 25,
        "Ny": 24,
        "Nxy": 15,
        "F": 0.6122448979591837,
        "F_value": "0.61"
    },
    "('I-IE', 'I-IIIB')": {
        "Nx": 25,
        "Ny": 25,
        "Nxy": 16,
        "F": 0.64,
        "F_value": "0.64"
    },
    "('I-IE', 'I-IP')": {
        "Nx": 25,
        "Ny": 22,
        "Nxy": 20,
        "F": 0.851063829787234,
        "F_value": "0.85"
    },
    "('I-IE', 'I-IVB')": {
        "Nx": 25,
        "Ny": 25,
        "Nxy": 19,
        "F": 0.76,
        "F_value": "0.76"
    },
    "('I-IE', 'I-VB')": {
        "Nx": 25,
        "Ny": 24,
        "Nxy": 20,
        "F": 0.8163265306122449,
        "F_value": "0.82"
    },
    "('I-IE', 'I-VIB')": {
        "Nx": 25,
        "Ny": 24,
        "Nxy": 20,
        "F": 0.8163265306122449,
        "F_value": "0.82"
    },
    "('I-IE', 'II-IA')": {
        "Nx": 25,
        "Ny": 24,
        "Nxy": 2,
        "F": 0.08163265306122448,
        "F_value": "0.08"
    },
    "('I-IE', 'IX-IB')": {
        "Nx": 25,
        "Ny": 22,
        "Nxy": 3,
        "F": 0.1276595744680851,
        "F_value": "0.13"
    },
    "('I-IE', 'IX-IH')": {
        "Nx": 25,
        "Ny": 20,
        "Nxy": 5,
        "F": 0.2222222222222222,
        "F_value": "0.22"
    },
    "('I-IE', 'V-IA')": {
        "Nx": 25,
        "Ny": 29,
        "Nxy": 3,
        "F": 0.1111111111111111,
        "F_value": "0.11"
    },
    "('I-IE', 'VII-IA')": {
        "Nx": 25,
        "Ny": 24,
        "Nxy": 5,
        "F": 0.20408163265306123,
        "F_value": "0.20"
    },
    "('I-IE', 'X-IA')": {
        "Nx": 25,
        "Ny": 19,
        "Nxy": 5,
        "F": 0.22727272727272727,
        "F_value": "0.23"
    },
    "('I-IE', 'X-IC')": {
        "Nx": 25,
        "Ny": 18,
        "Nxy": 6,
        "F": 0.27906976744186046,
        "F_value": "0.28"
    },
    "('I-IE', 'X-IF')": {
        "Nx": 25,
        "Ny": 19,
        "Nxy": 7,
        "F": 0.3181818181818182,
        "F_value": "0.32"
    },
    "('I-IE', 'XII-IA')": {
        "Nx": 25,
        "Ny": 22,
        "Nxy": 3,
        "F": 0.1276595744680851,
        "F_value": "0.13"
    },
    "('I-IE', 'XII-IB')": {
        "Nx": 25,
        "Ny": 23,
        "Nxy": 3,
        "F": 0.125,
        "F_value": "0.12"
    },
    "('I-IE', 'XIII-IA')": {
        "Nx": 25,
        "Ny": 29,
        "Nxy": 7,
        "F": 0.25925925925925924,
        "F_value": "0.26"
    },
    "('I-IE', 'XIV-IA')": {
        "Nx": 25,
        "Ny": 23,
        "Nxy": 1,
        "F": 0.041666666666666664,
        "F_value": "0.04"
    },
    "('I-IE', 'XIV-IC')": {
        "Nx": 25,
        "Ny": 23,
        "Nxy": 1,
        "F": 0.041666666666666664,
        "F_value": "0.04"
    },
    "('I-IF', 'I-IA')": {
        "Nx": 24,
        "Ny": 23,
        "Nxy": 19,
        "F": 0.8085106382978723,
        "F_value": "0.81"
    },
    "('I-IF', 'I-IB')": {
        "Nx": 24,
        "Ny": 25,
        "Nxy": 20,
        "F": 0.8163265306122449,
        "F_value": "0.82"
    },
    "('I-IF', 'I-IC')": {
        "Nx": 24,
        "Ny": 23,
        "Nxy": 19,
        "F": 0.8085106382978723,
        "F_value": "0.81"
    },
    "('I-IF', 'I-IE')": {
        "Nx": 24,
        "Ny": 25,
        "Nxy": 20,
        "F": 0.8163265306122449,
        "F_value": "0.82"
    },
    "('I-IF', 'I-IF')": {
        "Nx": 24,
        "Ny": 24,
        "Nxy": 24,
        "F": 1.0,
        "F_value": "1.00"
    },
    "('I-IF', 'I-IIA')": {
        "Nx": 24,
        "Ny": 24,
        "Nxy": 16,
        "F": 0.6666666666666666,
        "F_value": "0.67"
    },
    "('I-IF', 'I-IIB')": {
        "Nx": 24,
        "Ny": 24,
        "Nxy": 18,
        "F": 0.75,
        "F_value": "0.75"
    },
    "('I-IF', 'I-IIIB')": {
        "Nx": 24,
        "Ny": 25,
        "Nxy": 20,
        "F": 0.8163265306122449,
        "F_value": "0.82"
    },
    "('I-IF', 'I-IP')": {
        "Nx": 24,
        "Ny": 22,
        "Nxy": 17,
        "F": 0.7391304347826086,
        "F_value": "0.74"
    },
    "('I-IF', 'I-IVB')": {
        "Nx": 24,
        "Ny": 25,
        "Nxy": 23,
        "F": 0.9387755102040817,
        "F_value": "0.94"
    },
    "('I-IF', 'I-VB')": {
        "Nx": 24,
        "Ny": 24,
        "Nxy": 18,
        "F": 0.75,
        "F_value": "0.75"
    },
    "('I-IF', 'I-VIB')": {
        "Nx": 24,
        "Ny": 24,
        "Nxy": 18,
        "F": 0.75,
        "F_value": "0.75"
    },
    "('I-IF', 'II-IA')": {
        "Nx": 24,
        "Ny": 24,
        "Nxy": 2,
        "F": 0.08333333333333333,
        "F_value": "0.08"
    },
    "('I-IF', 'IX-IB')": {
        "Nx": 24,
        "Ny": 22,
        "Nxy": 2,
        "F": 0.08695652173913043,
        "F_value": "0.09"
    },
    "('I-IF', 'IX-IH')": {
        "Nx": 24,
        "Ny": 20,
        "Nxy": 4,
        "F": 0.18181818181818182,
        "F_value": "0.18"
    },
    "('I-IF', 'V-IA')": {
        "Nx": 24,
        "Ny": 29,
        "Nxy": 3,
        "F": 0.11320754716981132,
        "F_value": "0.11"
    },
    "('I-IF', 'VII-IA')": {
        "Nx": 24,
        "Ny": 24,
        "Nxy": 4,
        "F": 0.16666666666666666,
        "F_value": "0.17"
    },
    "('I-IF', 'X-IA')": {
        "Nx": 24,
        "Ny": 19,
        "Nxy": 5,
        "F": 0.23255813953488372,
        "F_value": "0.23"
    },
    "('I-IF', 'X-IC')": {
        "Nx": 24,
        "Ny": 18,
        "Nxy": 6,
        "F": 0.2857142857142857,
        "F_value": "0.29"
    },
    "('I-IF', 'X-IF')": {
        "Nx": 24,
        "Ny": 19,
        "Nxy": 7,
        "F": 0.32558139534883723,
        "F_value": "0.33"
    },
    "('I-IF', 'XII-IA')": {
        "Nx": 24,
        "Ny": 22,
        "Nxy": 3,
        "F": 0.13043478260869565,
        "F_value": "0.13"
    },
    "('I-IF', 'XII-IB')": {
        "Nx": 24,
        "Ny": 23,
        "Nxy": 3,
        "F": 0.1276595744680851,
        "F_value": "0.13"
    },
    "('I-IF', 'XIII-IA')": {
        "Nx": 24,
        "Ny": 29,
        "Nxy": 7,
        "F": 0.2641509433962264,
        "F_value": "0.26"
    },
    "('I-IF', 'XIV-IA')": {
        "Nx": 24,
        "Ny": 23,
        "Nxy": 1,
        "F": 0.0425531914893617,
        "F_value": "0.04"
    },
    "('I-IF', 'XIV-IC')": {
        "Nx": 24,
        "Ny": 23,
        "Nxy": 1,
        "F": 0.0425531914893617,
        "F_value": "0.04"
    },
    "('I-IIA', 'I-IA')": {
        "Nx": 24,
        "Ny": 23,
        "Nxy": 16,
        "F": 0.6808510638297872,
        "F_value": "0.68"
    },
    "('I-IIA', 'I-IB')": {
        "Nx": 24,
        "Ny": 25,
        "Nxy": 17,
        "F": 0.6938775510204082,
        "F_value": "0.69"
    },
    "('I-IIA', 'I-IC')": {
        "Nx": 24,
        "Ny": 23,
        "Nxy": 17,
        "F": 0.723404255319149,
        "F_value": "0.72"
    },
    "('I-IIA', 'I-IE')": {
        "Nx": 24,
        "Ny": 25,
        "Nxy": 15,
        "F": 0.6122448979591837,
        "F_value": "0.61"
    },
    "('I-IIA', 'I-IF')": {
        "Nx": 24,
        "Ny": 24,
        "Nxy": 16,
        "F": 0.6666666666666666,
        "F_value": "0.67"
    },
    "('I-IIA', 'I-IIA')": {
        "Nx": 24,
        "Ny": 24,
        "Nxy": 24,
        "F": 1.0,
        "F_value": "1.00"
    },
    "('I-IIA', 'I-IIB')": {
        "Nx": 24,
        "Ny": 24,
        "Nxy": 15,
        "F": 0.625,
        "F_value": "0.62"
    },
    "('I-IIA', 'I-IIIB')": {
        "Nx": 24,
        "Ny": 25,
        "Nxy": 15,
        "F": 0.6122448979591837,
        "F_value": "0.61"
    },
    "('I-IIA', 'I-IP')": {
        "Nx": 24,
        "Ny": 22,
        "Nxy": 12,
        "F": 0.5217391304347826,
        "F_value": "0.52"
    },
    "('I-IIA', 'I-IVB')": {
        "Nx": 24,
        "Ny": 25,
        "Nxy": 15,
        "F": 0.6122448979591837,
        "F_value": "0.61"
    },
    "('I-IIA', 'I-VB')": {
        "Nx": 24,
        "Ny": 24,
        "Nxy": 16,
        "F": 0.6666666666666666,
        "F_value": "0.67"
    },
    "('I-IIA', 'I-VIB')": {
        "Nx": 24,
        "Ny": 24,
        "Nxy": 16,
        "F": 0.6666666666666666,
        "F_value": "0.67"
    },
    "('I-IIA', 'II-IA')": {
        "Nx": 24,
        "Ny": 24,
        "Nxy": 1,
        "F": 0.041666666666666664,
        "F_value": "0.04"
    },
    "('I-IIA', 'IX-IB')": {
        "Nx": 24,
        "Ny": 22,
        "Nxy": 2,
        "F": 0.08695652173913043,
        "F_value": "0.09"
    },
    "('I-IIA', 'IX-IH')": {
        "Nx": 24,
        "Ny": 20,
        "Nxy": 4,
        "F": 0.18181818181818182,
        "F_value": "0.18"
    },
    "('I-IIA', 'V-IA')": {
        "Nx": 24,
        "Ny": 29,
        "Nxy": 5,
        "F": 0.18867924528301888,
        "F_value": "0.19"
    },
    "('I-IIA', 'VII-IA')": {
        "Nx": 24,
        "Ny": 24,
        "Nxy": 6,
        "F": 0.25,
        "F_value": "0.25"
    },
    "('I-IIA', 'X-IA')": {
        "Nx": 24,
        "Ny": 19,
        "Nxy": 3,
        "F": 0.13953488372093023,
        "F_value": "0.14"
    },
    "('I-IIA', 'X-IC')": {
        "Nx": 24,
        "Ny": 18,
        "Nxy": 3,
        "F": 0.14285714285714285,
        "F_value": "0.14"
    },
    "('I-IIA', 'X-IF')": {
        "Nx": 24,
        "Ny": 19,
        "Nxy": 4,
        "F": 0.18604651162790697,
        "F_value": "0.19"
    },
    "('I-IIA', 'XII-IA')": {
        "Nx": 24,
        "Ny": 22,
        "Nxy": 2,
        "F": 0.08695652173913043,
        "F_value": "0.09"
    },
    "('I-IIA', 'XII-IB')": {
        "Nx": 24,
        "Ny": 23,
        "Nxy": 2,
        "F": 0.0851063829787234,
        "F_value": "0.09"
    },
    "('I-IIA', 'XIII-IA')": {
        "Nx": 24,
        "Ny": 29,
        "Nxy": 5,
        "F": 0.18867924528301888,
        "F_value": "0.19"
    },
    "('I-IIA', 'XIV-IA')": {
        "Nx": 24,
        "Ny": 23,
        "Nxy": 0,
        "F": 0.0,
        "F_value": "0.00"
    },
    "('I-IIA', 'XIV-IC')": {
        "Nx": 24,
        "Ny": 23,
        "Nxy": 0,
        "F": 0.0,
        "F_value": "0.00"
    },
    "('I-IIB', 'I-IA')": {
        "Nx": 24,
        "Ny": 23,
        "Nxy": 17,
        "F": 0.723404255319149,
        "F_value": "0.72"
    },
    "('I-IIB', 'I-IB')": {
        "Nx": 24,
        "Ny": 25,
        "Nxy": 21,
        "F": 0.8571428571428571,
        "F_value": "0.86"
    },
    "('I-IIB', 'I-IC')": {
        "Nx": 24,
        "Ny": 23,
        "Nxy": 15,
        "F": 0.6382978723404256,
        "F_value": "0.64"
    },
    "('I-IIB', 'I-IE')": {
        "Nx": 24,
        "Ny": 25,
        "Nxy": 15,
        "F": 0.6122448979591837,
        "F_value": "0.61"
    },
    "('I-IIB', 'I-IF')": {
        "Nx": 24,
        "Ny": 24,
        "Nxy": 18,
        "F": 0.75,
        "F_value": "0.75"
    },
    "('I-IIB', 'I-IIA')": {
        "Nx": 24,
        "Ny": 24,
        "Nxy": 15,
        "F": 0.625,
        "F_value": "0.62"
    },
    "('I-IIB', 'I-IIB')": {
        "Nx": 24,
        "Ny": 24,
        "Nxy": 24,
        "F": 1.0,
        "F_value": "1.00"
    },
    "('I-IIB', 'I-IIIB')": {
        "Nx": 24,
        "Ny": 25,
        "Nxy": 23,
        "F": 0.9387755102040817,
        "F_value": "0.94"
    },
    "('I-IIB', 'I-IP')": {
        "Nx": 24,
        "Ny": 22,
        "Nxy": 12,
        "F": 0.5217391304347826,
        "F_value": "0.52"
    },
    "('I-IIB', 'I-IVB')": {
        "Nx": 24,
        "Ny": 25,
        "Nxy": 20,
        "F": 0.8163265306122449,
        "F_value": "0.82"
    },
    "('I-IIB', 'I-VB')": {
        "Nx": 24,
        "Ny": 24,
        "Nxy": 19,
        "F": 0.7916666666666666,
        "F_value": "0.79"
    },
    "('I-IIB', 'I-VIB')": {
        "Nx": 24,
        "Ny": 24,
        "Nxy": 19,
        "F": 0.7916666666666666,
        "F_value": "0.79"
    },
    "('I-IIB', 'II-IA')": {
        "Nx": 24,
        "Ny": 24,
        "Nxy": 1,
        "F": 0.041666666666666664,
        "F_value": "0.04"
    },
    "('I-IIB', 'IX-IB')": {
        "Nx": 24,
        "Ny": 22,
        "Nxy": 3,
        "F": 0.13043478260869565,
        "F_value": "0.13"
    },
    "('I-IIB', 'IX-IH')": {
        "Nx": 24,
        "Ny": 20,
        "Nxy": 5,
        "F": 0.22727272727272727,
        "F_value": "0.23"
    },
    "('I-IIB', 'V-IA')": {
        "Nx": 24,
        "Ny": 29,
        "Nxy": 5,
        "F": 0.18867924528301888,
        "F_value": "0.19"
    },
    "('I-IIB', 'VII-IA')": {
        "Nx": 24,
        "Ny": 24,
        "Nxy": 5,
        "F": 0.20833333333333334,
        "F_value": "0.21"
    },
    "('I-IIB', 'X-IA')": {
        "Nx": 24,
        "Ny": 19,
        "Nxy": 3,
        "F": 0.13953488372093023,
        "F_value": "0.14"
    },
    "('I-IIB', 'X-IC')": {
        "Nx": 24,
        "Ny": 18,
        "Nxy": 4,
        "F": 0.19047619047619047,
        "F_value": "0.19"
    },
    "('I-IIB', 'X-IF')": {
        "Nx": 24,
        "Ny": 19,
        "Nxy": 5,
        "F": 0.23255813953488372,
        "F_value": "0.23"
    },
    "('I-IIB', 'XII-IA')": {
        "Nx": 24,
        "Ny": 22,
        "Nxy": 3,
        "F": 0.13043478260869565,
        "F_value": "0.13"
    },
    "('I-IIB', 'XII-IB')": {
        "Nx": 24,
        "Ny": 23,
        "Nxy": 3,
        "F": 0.1276595744680851,
        "F_value": "0.13"
    },
    "('I-IIB', 'XIII-IA')": {
        "Nx": 24,
        "Ny": 29,
        "Nxy": 6,
        "F": 0.22641509433962265,
        "F_value": "0.23"
    },
    "('I-IIB', 'XIV-IA')": {
        "Nx": 24,
        "Ny": 23,
        "Nxy": 0,
        "F": 0.0,
        "F_value": "0.00"
    },
    "('I-IIB', 'XIV-IC')": {
        "Nx": 24,
        "Ny": 23,
        "Nxy": 0,
        "F": 0.0,
        "F_value": "0.00"
    },
    "('I-IIIB', 'I-IA')": {
        "Nx": 25,
        "Ny": 23,
        "Nxy": 18,
        "F": 0.75,
        "F_value": "0.75"
    },
    "('I-IIIB', 'I-IB')": {
        "Nx": 25,
        "Ny": 25,
        "Nxy": 22,
        "F": 0.88,
        "F_value": "0.88"
    },
    "('I-IIIB', 'I-IC')": {
        "Nx": 25,
        "Ny": 23,
        "Nxy": 16,
        "F": 0.6666666666666666,
        "F_value": "0.67"
    },
    "('I-IIIB', 'I-IE')": {
        "Nx": 25,
        "Ny": 25,
        "Nxy": 16,
        "F": 0.64,
        "F_value": "0.64"
    },
    "('I-IIIB', 'I-IF')": {
        "Nx": 25,
        "Ny": 24,
        "Nxy": 20,
        "F": 0.8163265306122449,
        "F_value": "0.82"
    },
    "('I-IIIB', 'I-IIA')": {
        "Nx": 25,
        "Ny": 24,
        "Nxy": 15,
        "F": 0.6122448979591837,
        "F_value": "0.61"
    },
    "('I-IIIB', 'I-IIB')": {
        "Nx": 25,
        "Ny": 24,
        "Nxy": 23,
        "F": 0.9387755102040817,
        "F_value": "0.94"
    },
    "('I-IIIB', 'I-IIIB')": {
        "Nx": 25,
        "Ny": 25,
        "Nxy": 25,
        "F": 1.0,
        "F_value": "1.00"
    },
    "('I-IIIB', 'I-IP')": {
        "Nx": 25,
        "Ny": 22,
        "Nxy": 13,
        "F": 0.5531914893617021,
        "F_value": "0.55"
    },
    "('I-IIIB', 'I-IVB')": {
        "Nx": 25,
        "Ny": 25,
        "Nxy": 22,
        "F": 0.88,
        "F_value": "0.88"
    },
    "('I-IIIB', 'I-VB')": {
        "Nx": 25,
        "Ny": 24,
        "Nxy": 20,
        "F": 0.8163265306122449,
        "F_value": "0.82"
    },
    "('I-IIIB', 'I-VIB')": {
        "Nx": 25,
        "Ny": 24,
        "Nxy": 20,
        "F": 0.8163265306122449,
        "F_value": "0.82"
    },
    "('I-IIIB', 'II-IA')": {
        "Nx": 25,
        "Ny": 24,
        "Nxy": 1,
        "F": 0.04081632653061224,
        "F_value": "0.04"
    },
    "('I-IIIB', 'IX-IB')": {
        "Nx": 25,
        "Ny": 22,
        "Nxy": 3,
        "F": 0.1276595744680851,
        "F_value": "0.13"
    },
    "('I-IIIB', 'IX-IH')": {
        "Nx": 25,
        "Ny": 20,
        "Nxy": 5,
        "F": 0.2222222222222222,
        "F_value": "0.22"
    },
    "('I-IIIB', 'V-IA')": {
        "Nx": 25,
        "Ny": 29,
        "Nxy": 5,
        "F": 0.18518518518518517,
        "F_value": "0.19"
    },
    "('I-IIIB', 'VII-IA')": {
        "Nx": 25,
        "Ny": 24,
        "Nxy": 5,
        "F": 0.20408163265306123,
        "F_value": "0.20"
    },
    "('I-IIIB', 'X-IA')": {
        "Nx": 25,
        "Ny": 19,
        "Nxy": 3,
        "F": 0.13636363636363635,
        "F_value": "0.14"
    },
    "('I-IIIB', 'X-IC')": {
        "Nx": 25,
        "Ny": 18,
        "Nxy": 4,
        "F": 0.18604651162790697,
        "F_value": "0.19"
    },
    "('I-IIIB', 'X-IF')": {
        "Nx": 25,
        "Ny": 19,
        "Nxy": 5,
        "F": 0.22727272727272727,
        "F_value": "0.23"
    },
    "('I-IIIB', 'XII-IA')": {
        "Nx": 25,
        "Ny": 22,
        "Nxy": 3,
        "F": 0.1276595744680851,
        "F_value": "0.13"
    },
    "('I-IIIB', 'XII-IB')": {
        "Nx": 25,
        "Ny": 23,
        "Nxy": 3,
        "F": 0.125,
        "F_value": "0.12"
    },
    "('I-IIIB', 'XIII-IA')": {
        "Nx": 25,
        "Ny": 29,
        "Nxy": 6,
        "F": 0.2222222222222222,
        "F_value": "0.22"
    },
    "('I-IIIB', 'XIV-IA')": {
        "Nx": 25,
        "Ny": 23,
        "Nxy": 0,
        "F": 0.0,
        "F_value": "0.00"
    },
    "('I-IIIB', 'XIV-IC')": {
        "Nx": 25,
        "Ny": 23,
        "Nxy": 0,
        "F": 0.0,
        "F_value": "0.00"
    },
    "('I-IP', 'I-IA')": {
        "Nx": 22,
        "Ny": 23,
        "Nxy": 16,
        "F": 0.7111111111111111,
        "F_value": "0.71"
    },
    "('I-IP', 'I-IB')": {
        "Nx": 22,
        "Ny": 25,
        "Nxy": 16,
        "F": 0.6808510638297872,
        "F_value": "0.68"
    },
    "('I-IP', 'I-IC')": {
        "Nx": 22,
        "Ny": 23,
        "Nxy": 16,
        "F": 0.7111111111111111,
        "F_value": "0.71"
    },
    "('I-IP', 'I-IE')": {
        "Nx": 22,
        "Ny": 25,
        "Nxy": 20,
        "F": 0.851063829787234,
        "F_value": "0.85"
    },
    "('I-IP', 'I-IF')": {
        "Nx": 22,
        "Ny": 24,
        "Nxy": 17,
        "F": 0.7391304347826086,
        "F_value": "0.74"
    },
    "('I-IP', 'I-IIA')": {
        "Nx": 22,
        "Ny": 24,
        "Nxy": 12,
        "F": 0.5217391304347826,
        "F_value": "0.52"
    },
    "('I-IP', 'I-IIB')": {
        "Nx": 22,
        "Ny": 24,
        "Nxy": 12,
        "F": 0.5217391304347826,
        "F_value": "0.52"
    },
    "('I-IP', 'I-IIIB')": {
        "Nx": 22,
        "Ny": 25,
        "Nxy": 13,
        "F": 0.5531914893617021,
        "F_value": "0.55"
    },
    "('I-IP', 'I-IP')": {
        "Nx": 22,
        "Ny": 22,
        "Nxy": 22,
        "F": 1.0,
        "F_value": "1.00"
    },
    "('I-IP', 'I-IVB')": {
        "Nx": 22,
        "Ny": 25,
        "Nxy": 16,
        "F": 0.6808510638297872,
        "F_value": "0.68"
    },
    "('I-IP', 'I-VB')": {
        "Nx": 22,
        "Ny": 24,
        "Nxy": 17,
        "F": 0.7391304347826086,
        "F_value": "0.74"
    },
    "('I-IP', 'I-VIB')": {
        "Nx": 22,
        "Ny": 24,
        "Nxy": 17,
        "F": 0.7391304347826086,
        "F_value": "0.74"
    },
    "('I-IP', 'II-IA')": {
        "Nx": 22,
        "Ny": 24,
        "Nxy": 2,
        "F": 0.08695652173913043,
        "F_value": "0.09"
    },
    "('I-IP', 'IX-IB')": {
        "Nx": 22,
        "Ny": 22,
        "Nxy": 3,
        "F": 0.13636363636363635,
        "F_value": "0.14"
    },
    "('I-IP', 'IX-IH')": {
        "Nx": 22,
        "Ny": 20,
        "Nxy": 6,
        "F": 0.2857142857142857,
        "F_value": "0.29"
    },
    "('I-IP', 'V-IA')": {
        "Nx": 22,
        "Ny": 29,
        "Nxy": 3,
        "F": 0.11764705882352941,
        "F_value": "0.12"
    },
    "('I-IP', 'VII-IA')": {
        "Nx": 22,
        "Ny": 24,
        "Nxy": 5,
        "F": 0.21739130434782608,
        "F_value": "0.22"
    },
    "('I-IP', 'X-IA')": {
        "Nx": 22,
        "Ny": 19,
        "Nxy": 6,
        "F": 0.2926829268292683,
        "F_value": "0.29"
    },
    "('I-IP', 'X-IC')": {
        "Nx": 22,
        "Ny": 18,
        "Nxy": 6,
        "F": 0.3,
        "F_value": "0.30"
    },
    "('I-IP', 'X-IF')": {
        "Nx": 22,
        "Ny": 19,
        "Nxy": 8,
        "F": 0.3902439024390244,
        "F_value": "0.39"
    },
    "('I-IP', 'XII-IA')": {
        "Nx": 22,
        "Ny": 22,
        "Nxy": 3,
        "F": 0.13636363636363635,
        "F_value": "0.14"
    },
    "('I-IP', 'XII-IB')": {
        "Nx": 22,
        "Ny": 23,
        "Nxy": 3,
        "F": 0.13333333333333333,
        "F_value": "0.13"
    },
    "('I-IP', 'XIII-IA')": {
        "Nx": 22,
        "Ny": 29,
        "Nxy": 7,
        "F": 0.27450980392156865,
        "F_value": "0.27"
    },
    "('I-IP', 'XIV-IA')": {
        "Nx": 22,
        "Ny": 23,
        "Nxy": 1,
        "F": 0.044444444444444446,
        "F_value": "0.04"
    },
    "('I-IP', 'XIV-IC')": {
        "Nx": 22,
        "Ny": 23,
        "Nxy": 1,
        "F": 0.044444444444444446,
        "F_value": "0.04"
    },
    "('I-IVB', 'I-IA')": {
        "Nx": 25,
        "Ny": 23,
        "Nxy": 18,
        "F": 0.75,
        "F_value": "0.75"
    },
    "('I-IVB', 'I-IB')": {
        "Nx": 25,
        "Ny": 25,
        "Nxy": 19,
        "F": 0.76,
        "F_value": "0.76"
    },
    "('I-IVB', 'I-IC')": {
        "Nx": 25,
        "Ny": 23,
        "Nxy": 19,
        "F": 0.7916666666666666,
        "F_value": "0.79"
    },
    "('I-IVB', 'I-IE')": {
        "Nx": 25,
        "Ny": 25,
        "Nxy": 19,
        "F": 0.76,
        "F_value": "0.76"
    },
    "('I-IVB', 'I-IF')": {
        "Nx": 25,
        "Ny": 24,
        "Nxy": 23,
        "F": 0.9387755102040817,
        "F_value": "0.94"
    },
    "('I-IVB', 'I-IIA')": {
        "Nx": 25,
        "Ny": 24,
        "Nxy": 15,
        "F": 0.6122448979591837,
        "F_value": "0.61"
    },
    "('I-IVB', 'I-IIB')": {
        "Nx": 25,
        "Ny": 24,
        "Nxy": 20,
        "F": 0.8163265306122449,
        "F_value": "0.82"
    },
    "('I-IVB', 'I-IIIB')": {
        "Nx": 25,
        "Ny": 25,
        "Nxy": 22,
        "F": 0.88,
        "F_value": "0.88"
    },
    "('I-IVB', 'I-IP')": {
        "Nx": 25,
        "Ny": 22,
        "Nxy": 16,
        "F": 0.6808510638297872,
        "F_value": "0.68"
    },
    "('I-IVB', 'I-IVB')": {
        "Nx": 25,
        "Ny": 25,
        "Nxy": 25,
        "F": 1.0,
        "F_value": "1.00"
    },
    "('I-IVB', 'I-VB')": {
        "Nx": 25,
        "Ny": 24,
        "Nxy": 17,
        "F": 0.6938775510204082,
        "F_value": "0.69"
    },
    "('I-IVB', 'I-VIB')": {
        "Nx": 25,
        "Ny": 24,
        "Nxy": 17,
        "F": 0.6938775510204082,
        "F_value": "0.69"
    },
    "('I-IVB', 'II-IA')": {
        "Nx": 25,
        "Ny": 24,
        "Nxy": 2,
        "F": 0.08163265306122448,
        "F_value": "0.08"
    },
    "('I-IVB', 'IX-IB')": {
        "Nx": 25,
        "Ny": 22,
        "Nxy": 2,
        "F": 0.0851063829787234,
        "F_value": "0.09"
    },
    "('I-IVB', 'IX-IH')": {
        "Nx": 25,
        "Ny": 20,
        "Nxy": 4,
        "F": 0.17777777777777778,
        "F_value": "0.18"
    },
    "('I-IVB', 'V-IA')": {
        "Nx": 25,
        "Ny": 29,
        "Nxy": 4,
        "F": 0.14814814814814814,
        "F_value": "0.15"
    },
    "('I-IVB', 'VII-IA')": {
        "Nx": 25,
        "Ny": 24,
        "Nxy": 4,
        "F": 0.16326530612244897,
        "F_value": "0.16"
    },
    "('I-IVB', 'X-IA')": {
        "Nx": 25,
        "Ny": 19,
        "Nxy": 5,
        "F": 0.22727272727272727,
        "F_value": "0.23"
    },
    "('I-IVB', 'X-IC')": {
        "Nx": 25,
        "Ny": 18,
        "Nxy": 6,
        "F": 0.27906976744186046,
        "F_value": "0.28"
    },
    "('I-IVB', 'X-IF')": {
        "Nx": 25,
        "Ny": 19,
        "Nxy": 7,
        "F": 0.3181818181818182,
        "F_value": "0.32"
    },
    "('I-IVB', 'XII-IA')": {
        "Nx": 25,
        "Ny": 22,
        "Nxy": 3,
        "F": 0.1276595744680851,
        "F_value": "0.13"
    },
    "('I-IVB', 'XII-IB')": {
        "Nx": 25,
        "Ny": 23,
        "Nxy": 3,
        "F": 0.125,
        "F_value": "0.12"
    },
    "('I-IVB', 'XIII-IA')": {
        "Nx": 25,
        "Ny": 29,
        "Nxy": 7,
        "F": 0.25925925925925924,
        "F_value": "0.26"
    },
    "('I-IVB', 'XIV-IA')": {
        "Nx": 25,
        "Ny": 23,
        "Nxy": 1,
        "F": 0.041666666666666664,
        "F_value": "0.04"
    },
    "('I-IVB', 'XIV-IC')": {
        "Nx": 25,
        "Ny": 23,
        "Nxy": 1,
        "F": 0.041666666666666664,
        "F_value": "0.04"
    },
    "('I-VB', 'I-IA')": {
        "Nx": 24,
        "Ny": 23,
        "Nxy": 20,
        "F": 0.851063829787234,
        "F_value": "0.85"
    },
    "('I-VB', 'I-IB')": {
        "Nx": 24,
        "Ny": 25,
        "Nxy": 23,
        "F": 0.9387755102040817,
        "F_value": "0.94"
    },
    "('I-VB', 'I-IC')": {
        "Nx": 24,
        "Ny": 23,
        "Nxy": 17,
        "F": 0.723404255319149,
        "F_value": "0.72"
    },
    "('I-VB', 'I-IE')": {
        "Nx": 24,
        "Ny": 25,
        "Nxy": 20,
        "F": 0.8163265306122449,
        "F_value": "0.82"
    },
    "('I-VB', 'I-IF')": {
        "Nx": 24,
        "Ny": 24,
        "Nxy": 18,
        "F": 0.75,
        "F_value": "0.75"
    },
    "('I-VB', 'I-IIA')": {
        "Nx": 24,
        "Ny": 24,
        "Nxy": 16,
        "F": 0.6666666666666666,
        "F_value": "0.67"
    },
    "('I-VB', 'I-IIB')": {
        "Nx": 24,
        "Ny": 24,
        "Nxy": 19,
        "F": 0.7916666666666666,
        "F_value": "0.79"
    },
    "('I-VB', 'I-IIIB')": {
        "Nx": 24,
        "Ny": 25,
        "Nxy": 20,
        "F": 0.8163265306122449,
        "F_value": "0.82"
    },
    "('I-VB', 'I-IP')": {
        "Nx": 24,
        "Ny": 22,
        "Nxy": 17,
        "F": 0.7391304347826086,
        "F_value": "0.74"
    },
    "('I-VB', 'I-IVB')": {
        "Nx": 24,
        "Ny": 25,
        "Nxy": 17,
        "F": 0.6938775510204082,
        "F_value": "0.69"
    },
    "('I-VB', 'I-VB')": {
        "Nx": 24,
        "Ny": 24,
        "Nxy": 24,
        "F": 1.0,
        "F_value": "1.00"
    },
    "('I-VB', 'I-VIB')": {
        "Nx": 24,
        "Ny": 24,
        "Nxy": 24,
        "F": 1.0,
        "F_value": "1.00"
    },
    "('I-VB', 'II-IA')": {
        "Nx": 24,
        "Ny": 24,
        "Nxy": 1,
        "F": 0.041666666666666664,
        "F_value": "0.04"
    },
    "('I-VB', 'IX-IB')": {
        "Nx": 24,
        "Ny": 22,
        "Nxy": 4,
        "F": 0.17391304347826086,
        "F_value": "0.17"
    },
    "('I-VB', 'IX-IH')": {
        "Nx": 24,
        "Ny": 20,
        "Nxy": 6,
        "F": 0.2727272727272727,
        "F_value": "0.27"
    },
    "('I-VB', 'V-IA')": {
        "Nx": 24,
        "Ny": 29,
        "Nxy": 4,
        "F": 0.1509433962264151,
        "F_value": "0.15"
    },
    "('I-VB', 'VII-IA')": {
        "Nx": 24,
        "Ny": 24,
        "Nxy": 5,
        "F": 0.20833333333333334,
        "F_value": "0.21"
    },
    "('I-VB', 'X-IA')": {
        "Nx": 24,
        "Ny": 19,
        "Nxy": 3,
        "F": 0.13953488372093023,
        "F_value": "0.14"
    },
    "('I-VB', 'X-IC')": {
        "Nx": 24,
        "Ny": 18,
        "Nxy": 4,
        "F": 0.19047619047619047,
        "F_value": "0.19"
    },
    "('I-VB', 'X-IF')": {
        "Nx": 24,
        "Ny": 19,
        "Nxy": 5,
        "F": 0.23255813953488372,
        "F_value": "0.23"
    },
    "('I-VB', 'XII-IA')": {
        "Nx": 24,
        "Ny": 22,
        "Nxy": 3,
        "F": 0.13043478260869565,
        "F_value": "0.13"
    },
    "('I-VB', 'XII-IB')": {
        "Nx": 24,
        "Ny": 23,
        "Nxy": 3,
        "F": 0.1276595744680851,
        "F_value": "0.13"
    },
    "('I-VB', 'XIII-IA')": {
        "Nx": 24,
        "Ny": 29,
        "Nxy": 6,
        "F": 0.22641509433962265,
        "F_value": "0.23"
    },
    "('I-VB', 'XIV-IA')": {
        "Nx": 24,
        "Ny": 23,
        "Nxy": 0,
        "F": 0.0,
        "F_value": "0.00"
    },
    "('I-VB', 'XIV-IC')": {
        "Nx": 24,
        "Ny": 23,
        "Nxy": 0,
        "F": 0.0,
        "F_value": "0.00"
    },
    "('I-VIB', 'I-IA')": {
        "Nx": 24,
        "Ny": 23,
        "Nxy": 20,
        "F": 0.851063829787234,
        "F_value": "0.85"
    },
    "('I-VIB', 'I-IB')": {
        "Nx": 24,
        "Ny": 25,
        "Nxy": 23,
        "F": 0.9387755102040817,
        "F_value": "0.94"
    },
    "('I-VIB', 'I-IC')": {
        "Nx": 24,
        "Ny": 23,
        "Nxy": 17,
        "F": 0.723404255319149,
        "F_value": "0.72"
    },
    "('I-VIB', 'I-IE')": {
        "Nx": 24,
        "Ny": 25,
        "Nxy": 20,
        "F": 0.8163265306122449,
        "F_value": "0.82"
    },
    "('I-VIB', 'I-IF')": {
        "Nx": 24,
        "Ny": 24,
        "Nxy": 18,
        "F": 0.75,
        "F_value": "0.75"
    },
    "('I-VIB', 'I-IIA')": {
        "Nx": 24,
        "Ny": 24,
        "Nxy": 16,
        "F": 0.6666666666666666,
        "F_value": "0.67"
    },
    "('I-VIB', 'I-IIB')": {
        "Nx": 24,
        "Ny": 24,
        "Nxy": 19,
        "F": 0.7916666666666666,
        "F_value": "0.79"
    },
    "('I-VIB', 'I-IIIB')": {
        "Nx": 24,
        "Ny": 25,
        "Nxy": 20,
        "F": 0.8163265306122449,
        "F_value": "0.82"
    },
    "('I-VIB', 'I-IP')": {
        "Nx": 24,
        "Ny": 22,
        "Nxy": 17,
        "F": 0.7391304347826086,
        "F_value": "0.74"
    },
    "('I-VIB', 'I-IVB')": {
        "Nx": 24,
        "Ny": 25,
        "Nxy": 17,
        "F": 0.6938775510204082,
        "F_value": "0.69"
    },
    "('I-VIB', 'I-VB')": {
        "Nx": 24,
        "Ny": 24,
        "Nxy": 24,
        "F": 1.0,
        "F_value": "1.00"
    },
    "('I-VIB', 'I-VIB')": {
        "Nx": 24,
        "Ny": 24,
        "Nxy": 24,
        "F": 1.0,
        "F_value": "1.00"
    },
    "('I-VIB', 'II-IA')": {
        "Nx": 24,
        "Ny": 24,
        "Nxy": 1,
        "F": 0.041666666666666664,
        "F_value": "0.04"
    },
    "('I-VIB', 'IX-IB')": {
        "Nx": 24,
        "Ny": 22,
        "Nxy": 4,
        "F": 0.17391304347826086,
        "F_value": "0.17"
    },
    "('I-VIB', 'IX-IH')": {
        "Nx": 24,
        "Ny": 20,
        "Nxy": 6,
        "F": 0.2727272727272727,
        "F_value": "0.27"
    },
    "('I-VIB', 'V-IA')": {
        "Nx": 24,
        "Ny": 29,
        "Nxy": 4,
        "F": 0.1509433962264151,
        "F_value": "0.15"
    },
    "('I-VIB', 'VII-IA')": {
        "Nx": 24,
        "Ny": 24,
        "Nxy": 5,
        "F": 0.20833333333333334,
        "F_value": "0.21"
    },
    "('I-VIB', 'X-IA')": {
        "Nx": 24,
        "Ny": 19,
        "Nxy": 3,
        "F": 0.13953488372093023,
        "F_value": "0.14"
    },
    "('I-VIB', 'X-IC')": {
        "Nx": 24,
        "Ny": 18,
        "Nxy": 4,
        "F": 0.19047619047619047,
        "F_value": "0.19"
    },
    "('I-VIB', 'X-IF')": {
        "Nx": 24,
        "Ny": 19,
        "Nxy": 5,
        "F": 0.23255813953488372,
        "F_value": "0.23"
    },
    "('I-VIB', 'XII-IA')": {
        "Nx": 24,
        "Ny": 22,
        "Nxy": 3,
        "F": 0.13043478260869565,
        "F_value": "0.13"
    },
    "('I-VIB', 'XII-IB')": {
        "Nx": 24,
        "Ny": 23,
        "Nxy": 3,
        "F": 0.1276595744680851,
        "F_value": "0.13"
    },
    "('I-VIB', 'XIII-IA')": {
        "Nx": 24,
        "Ny": 29,
        "Nxy": 6,
        "F": 0.22641509433962265,
        "F_value": "0.23"
    },
    "('I-VIB', 'XIV-IA')": {
        "Nx": 24,
        "Ny": 23,
        "Nxy": 0,
        "F": 0.0,
        "F_value": "0.00"
    },
    "('I-VIB', 'XIV-IC')": {
        "Nx": 24,
        "Ny": 23,
        "Nxy": 0,
        "F": 0.0,
        "F_value": "0.00"
    },
    "('II-IA', 'I-IA')": {
        "Nx": 24,
        "Ny": 23,
        "Nxy": 1,
        "F": 0.0425531914893617,
        "F_value": "0.04"
    },
    "('II-IA', 'I-IB')": {
        "Nx": 24,
        "Ny": 25,
        "Nxy": 1,
        "F": 0.04081632653061224,
        "F_value": "0.04"
    },
    "('II-IA', 'I-IC')": {
        "Nx": 24,
        "Ny": 23,
        "Nxy": 2,
        "F": 0.0851063829787234,
        "F_value": "0.09"
    },
    "('II-IA', 'I-IE')": {
        "Nx": 24,
        "Ny": 25,
        "Nxy": 2,
        "F": 0.08163265306122448,
        "F_value": "0.08"
    },
    "('II-IA', 'I-IF')": {
        "Nx": 24,
        "Ny": 24,
        "Nxy": 2,
        "F": 0.08333333333333333,
        "F_value": "0.08"
    },
    "('II-IA', 'I-IIA')": {
        "Nx": 24,
        "Ny": 24,
        "Nxy": 1,
        "F": 0.041666666666666664,
        "F_value": "0.04"
    },
    "('II-IA', 'I-IIB')": {
        "Nx": 24,
        "Ny": 24,
        "Nxy": 1,
        "F": 0.041666666666666664,
        "F_value": "0.04"
    },
    "('II-IA', 'I-IIIB')": {
        "Nx": 24,
        "Ny": 25,
        "Nxy": 1,
        "F": 0.04081632653061224,
        "F_value": "0.04"
    },
    "('II-IA', 'I-IP')": {
        "Nx": 24,
        "Ny": 22,
        "Nxy": 2,
        "F": 0.08695652173913043,
        "F_value": "0.09"
    },
    "('II-IA', 'I-IVB')": {
        "Nx": 24,
        "Ny": 25,
        "Nxy": 2,
        "F": 0.08163265306122448,
        "F_value": "0.08"
    },
    "('II-IA', 'I-VB')": {
        "Nx": 24,
        "Ny": 24,
        "Nxy": 1,
        "F": 0.041666666666666664,
        "F_value": "0.04"
    },
    "('II-IA', 'I-VIB')": {
        "Nx": 24,
        "Ny": 24,
        "Nxy": 1,
        "F": 0.041666666666666664,
        "F_value": "0.04"
    },
    "('II-IA', 'II-IA')": {
        "Nx": 24,
        "Ny": 24,
        "Nxy": 24,
        "F": 1.0,
        "F_value": "1.00"
    },
    "('II-IA', 'IX-IB')": {
        "Nx": 24,
        "Ny": 22,
        "Nxy": 2,
        "F": 0.08695652173913043,
        "F_value": "0.09"
    },
    "('II-IA', 'IX-IH')": {
        "Nx": 24,
        "Ny": 20,
        "Nxy": 2,
        "F": 0.09090909090909091,
        "F_value": "0.09"
    },
    "('II-IA', 'V-IA')": {
        "Nx": 24,
        "Ny": 29,
        "Nxy": 3,
        "F": 0.11320754716981132,
        "F_value": "0.11"
    },
    "('II-IA', 'VII-IA')": {
        "Nx": 24,
        "Ny": 24,
        "Nxy": 2,
        "F": 0.08333333333333333,
        "F_value": "0.08"
    },
    "('II-IA', 'X-IA')": {
        "Nx": 24,
        "Ny": 19,
        "Nxy": 3,
        "F": 0.13953488372093023,
        "F_value": "0.14"
    },
    "('II-IA', 'X-IC')": {
        "Nx": 24,
        "Ny": 18,
        "Nxy": 3,
        "F": 0.14285714285714285,
        "F_value": "0.14"
    },
    "('II-IA', 'X-IF')": {
        "Nx": 24,
        "Ny": 19,
        "Nxy": 3,
        "F": 0.13953488372093023,
        "F_value": "0.14"
    },
    "('II-IA', 'XII-IA')": {
        "Nx": 24,
        "Ny": 22,
        "Nxy": 2,
        "F": 0.08695652173913043,
        "F_value": "0.09"
    },
    "('II-IA', 'XII-IB')": {
        "Nx": 24,
        "Ny": 23,
        "Nxy": 2,
        "F": 0.0851063829787234,
        "F_value": "0.09"
    },
    "('II-IA', 'XIII-IA')": {
        "Nx": 24,
        "Ny": 29,
        "Nxy": 2,
        "F": 0.07547169811320754,
        "F_value": "0.08"
    },
    "('II-IA', 'XIV-IA')": {
        "Nx": 24,
        "Ny": 23,
        "Nxy": 4,
        "F": 0.1702127659574468,
        "F_value": "0.17"
    },
    "('II-IA', 'XIV-IC')": {
        "Nx": 24,
        "Ny": 23,
        "Nxy": 4,
        "F": 0.1702127659574468,
        "F_value": "0.17"
    },
    "('IX-IB', 'I-IA')": {
        "Nx": 22,
        "Ny": 23,
        "Nxy": 4,
        "F": 0.17777777777777778,
        "F_value": "0.18"
    },
    "('IX-IB', 'I-IB')": {
        "Nx": 22,
        "Ny": 25,
        "Nxy": 4,
        "F": 0.1702127659574468,
        "F_value": "0.17"
    },
    "('IX-IB', 'I-IC')": {
        "Nx": 22,
        "Ny": 23,
        "Nxy": 3,
        "F": 0.13333333333333333,
        "F_value": "0.13"
    },
    "('IX-IB', 'I-IE')": {
        "Nx": 22,
        "Ny": 25,
        "Nxy": 3,
        "F": 0.1276595744680851,
        "F_value": "0.13"
    },
    "('IX-IB', 'I-IF')": {
        "Nx": 22,
        "Ny": 24,
        "Nxy": 2,
        "F": 0.08695652173913043,
        "F_value": "0.09"
    },
    "('IX-IB', 'I-IIA')": {
        "Nx": 22,
        "Ny": 24,
        "Nxy": 2,
        "F": 0.08695652173913043,
        "F_value": "0.09"
    },
    "('IX-IB', 'I-IIB')": {
        "Nx": 22,
        "Ny": 24,
        "Nxy": 3,
        "F": 0.13043478260869565,
        "F_value": "0.13"
    },
    "('IX-IB', 'I-IIIB')": {
        "Nx": 22,
        "Ny": 25,
        "Nxy": 3,
        "F": 0.1276595744680851,
        "F_value": "0.13"
    },
    "('IX-IB', 'I-IP')": {
        "Nx": 22,
        "Ny": 22,
        "Nxy": 3,
        "F": 0.13636363636363635,
        "F_value": "0.14"
    },
    "('IX-IB', 'I-IVB')": {
        "Nx": 22,
        "Ny": 25,
        "Nxy": 2,
        "F": 0.0851063829787234,
        "F_value": "0.09"
    },
    "('IX-IB', 'I-VB')": {
        "Nx": 22,
        "Ny": 24,
        "Nxy": 4,
        "F": 0.17391304347826086,
        "F_value": "0.17"
    },
    "('IX-IB', 'I-VIB')": {
        "Nx": 22,
        "Ny": 24,
        "Nxy": 4,
        "F": 0.17391304347826086,
        "F_value": "0.17"
    },
    "('IX-IB', 'II-IA')": {
        "Nx": 22,
        "Ny": 24,
        "Nxy": 2,
        "F": 0.08695652173913043,
        "F_value": "0.09"
    },
    "('IX-IB', 'IX-IB')": {
        "Nx": 22,
        "Ny": 22,
        "Nxy": 22,
        "F": 1.0,
        "F_value": "1.00"
    },
    "('IX-IB', 'IX-IH')": {
        "Nx": 22,
        "Ny": 20,
        "Nxy": 10,
        "F": 0.47619047619047616,
        "F_value": "0.48"
    },
    "('IX-IB', 'V-IA')": {
        "Nx": 22,
        "Ny": 29,
        "Nxy": 3,
        "F": 0.11764705882352941,
        "F_value": "0.12"
    },
    "('IX-IB', 'VII-IA')": {
        "Nx": 22,
        "Ny": 24,
        "Nxy": 3,
        "F": 0.13043478260869565,
        "F_value": "0.13"
    },
    "('IX-IB', 'X-IA')": {
        "Nx": 22,
        "Ny": 19,
        "Nxy": 2,
        "F": 0.0975609756097561,
        "F_value": "0.10"
    },
    "('IX-IB', 'X-IC')": {
        "Nx": 22,
        "Ny": 18,
        "Nxy": 4,
        "F": 0.2,
        "F_value": "0.20"
    },
    "('IX-IB', 'X-IF')": {
        "Nx": 22,
        "Ny": 19,
        "Nxy": 3,
        "F": 0.14634146341463414,
        "F_value": "0.15"
    },
    "('IX-IB', 'XII-IA')": {
        "Nx": 22,
        "Ny": 22,
        "Nxy": 4,
        "F": 0.18181818181818182,
        "F_value": "0.18"
    },
    "('IX-IB', 'XII-IB')": {
        "Nx": 22,
        "Ny": 23,
        "Nxy": 5,
        "F": 0.2222222222222222,
        "F_value": "0.22"
    },
    "('IX-IB', 'XIII-IA')": {
        "Nx": 22,
        "Ny": 29,
        "Nxy": 2,
        "F": 0.0784313725490196,
        "F_value": "0.08"
    },
    "('IX-IB', 'XIV-IA')": {
        "Nx": 22,
        "Ny": 23,
        "Nxy": 1,
        "F": 0.044444444444444446,
        "F_value": "0.04"
    },
    "('IX-IB', 'XIV-IC')": {
        "Nx": 22,
        "Ny": 23,
        "Nxy": 0,
        "F": 0.0,
        "F_value": "0.00"
    },
    "('IX-IH', 'I-IA')": {
        "Nx": 20,
        "Ny": 23,
        "Nxy": 6,
        "F": 0.27906976744186046,
        "F_value": "0.28"
    },
    "('IX-IH', 'I-IB')": {
        "Nx": 20,
        "Ny": 25,
        "Nxy": 6,
        "F": 0.26666666666666666,
        "F_value": "0.27"
    },
    "('IX-IH', 'I-IC')": {
        "Nx": 20,
        "Ny": 23,
        "Nxy": 5,
        "F": 0.23255813953488372,
        "F_value": "0.23"
    },
    "('IX-IH', 'I-IE')": {
        "Nx": 20,
        "Ny": 25,
        "Nxy": 5,
        "F": 0.2222222222222222,
        "F_value": "0.22"
    },
    "('IX-IH', 'I-IF')": {
        "Nx": 20,
        "Ny": 24,
        "Nxy": 4,
        "F": 0.18181818181818182,
        "F_value": "0.18"
    },
    "('IX-IH', 'I-IIA')": {
        "Nx": 20,
        "Ny": 24,
        "Nxy": 4,
        "F": 0.18181818181818182,
        "F_value": "0.18"
    },
    "('IX-IH', 'I-IIB')": {
        "Nx": 20,
        "Ny": 24,
        "Nxy": 5,
        "F": 0.22727272727272727,
        "F_value": "0.23"
    },
    "('IX-IH', 'I-IIIB')": {
        "Nx": 20,
        "Ny": 25,
        "Nxy": 5,
        "F": 0.2222222222222222,
        "F_value": "0.22"
    },
    "('IX-IH', 'I-IP')": {
        "Nx": 20,
        "Ny": 22,
        "Nxy": 6,
        "F": 0.2857142857142857,
        "F_value": "0.29"
    },
    "('IX-IH', 'I-IVB')": {
        "Nx": 20,
        "Ny": 25,
        "Nxy": 4,
        "F": 0.17777777777777778,
        "F_value": "0.18"
    },
    "('IX-IH', 'I-VB')": {
        "Nx": 20,
        "Ny": 24,
        "Nxy": 6,
        "F": 0.2727272727272727,
        "F_value": "0.27"
    },
    "('IX-IH', 'I-VIB')": {
        "Nx": 20,
        "Ny": 24,
        "Nxy": 6,
        "F": 0.2727272727272727,
        "F_value": "0.27"
    },
    "('IX-IH', 'II-IA')": {
        "Nx": 20,
        "Ny": 24,
        "Nxy": 2,
        "F": 0.09090909090909091,
        "F_value": "0.09"
    },
    "('IX-IH', 'IX-IB')": {
        "Nx": 20,
        "Ny": 22,
        "Nxy": 10,
        "F": 0.47619047619047616,
        "F_value": "0.48"
    },
    "('IX-IH', 'IX-IH')": {
        "Nx": 20,
        "Ny": 20,
        "Nxy": 20,
        "F": 1.0,
        "F_value": "1.00"
    },
    "('IX-IH', 'V-IA')": {
        "Nx": 20,
        "Ny": 29,
        "Nxy": 7,
        "F": 0.2857142857142857,
        "F_value": "0.29"
    },
    "('IX-IH', 'VII-IA')": {
        "Nx": 20,
        "Ny": 24,
        "Nxy": 8,
        "F": 0.36363636363636365,
        "F_value": "0.36"
    },
    "('IX-IH', 'X-IA')": {
        "Nx": 20,
        "Ny": 19,
        "Nxy": 5,
        "F": 0.2564102564102564,
        "F_value": "0.26"
    },
    "('IX-IH', 'X-IC')": {
        "Nx": 20,
        "Ny": 18,
        "Nxy": 5,
        "F": 0.2631578947368421,
        "F_value": "0.26"
    },
    "('IX-IH', 'X-IF')": {
        "Nx": 20,
        "Ny": 19,
        "Nxy": 6,
        "F": 0.3076923076923077,
        "F_value": "0.31"
    },
    "('IX-IH', 'XII-IA')": {
        "Nx": 20,
        "Ny": 22,
        "Nxy": 4,
        "F": 0.19047619047619047,
        "F_value": "0.19"
    },
    "('IX-IH', 'XII-IB')": {
        "Nx": 20,
        "Ny": 23,
        "Nxy": 4,
        "F": 0.18604651162790697,
        "F_value": "0.19"
    },
    "('IX-IH', 'XIII-IA')": {
        "Nx": 20,
        "Ny": 29,
        "Nxy": 6,
        "F": 0.24489795918367346,
        "F_value": "0.24"
    },
    "('IX-IH', 'XIV-IA')": {
        "Nx": 20,
        "Ny": 23,
        "Nxy": 1,
        "F": 0.046511627906976744,
        "F_value": "0.05"
    },
    "('IX-IH', 'XIV-IC')": {
        "Nx": 20,
        "Ny": 23,
        "Nxy": 1,
        "F": 0.046511627906976744,
        "F_value": "0.05"
    },
    "('V-IA', 'I-IA')": {
        "Nx": 29,
        "Ny": 23,
        "Nxy": 4,
        "F": 0.15384615384615385,
        "F_value": "0.15"
    },
    "('V-IA', 'I-IB')": {
        "Nx": 29,
        "Ny": 25,
        "Nxy": 4,
        "F": 0.14814814814814814,
        "F_value": "0.15"
    },
    "('V-IA', 'I-IC')": {
        "Nx": 29,
        "Ny": 23,
        "Nxy": 3,
        "F": 0.11538461538461539,
        "F_value": "0.12"
    },
    "('V-IA', 'I-IE')": {
        "Nx": 29,
        "Ny": 25,
        "Nxy": 3,
        "F": 0.1111111111111111,
        "F_value": "0.11"
    },
    "('V-IA', 'I-IF')": {
        "Nx": 29,
        "Ny": 24,
        "Nxy": 3,
        "F": 0.11320754716981132,
        "F_value": "0.11"
    },
    "('V-IA', 'I-IIA')": {
        "Nx": 29,
        "Ny": 24,
        "Nxy": 5,
        "F": 0.18867924528301888,
        "F_value": "0.19"
    },
    "('V-IA', 'I-IIB')": {
        "Nx": 29,
        "Ny": 24,
        "Nxy": 5,
        "F": 0.18867924528301888,
        "F_value": "0.19"
    },
    "('V-IA', 'I-IIIB')": {
        "Nx": 29,
        "Ny": 25,
        "Nxy": 5,
        "F": 0.18518518518518517,
        "F_value": "0.19"
    },
    "('V-IA', 'I-IP')": {
        "Nx": 29,
        "Ny": 22,
        "Nxy": 3,
        "F": 0.11764705882352941,
        "F_value": "0.12"
    },
    "('V-IA', 'I-IVB')": {
        "Nx": 29,
        "Ny": 25,
        "Nxy": 4,
        "F": 0.14814814814814814,
        "F_value": "0.15"
    },
    "('V-IA', 'I-VB')": {
        "Nx": 29,
        "Ny": 24,
        "Nxy": 4,
        "F": 0.1509433962264151,
        "F_value": "0.15"
    },
    "('V-IA', 'I-VIB')": {
        "Nx": 29,
        "Ny": 24,
        "Nxy": 4,
        "F": 0.1509433962264151,
        "F_value": "0.15"
    },
    "('V-IA', 'II-IA')": {
        "Nx": 29,
        "Ny": 24,
        "Nxy": 3,
        "F": 0.11320754716981132,
        "F_value": "0.11"
    },
    "('V-IA', 'IX-IB')": {
        "Nx": 29,
        "Ny": 22,
        "Nxy": 3,
        "F": 0.11764705882352941,
        "F_value": "0.12"
    },
    "('V-IA', 'IX-IH')": {
        "Nx": 29,
        "Ny": 20,
        "Nxy": 7,
        "F": 0.2857142857142857,
        "F_value": "0.29"
    },
    "('V-IA', 'V-IA')": {
        "Nx": 29,
        "Ny": 29,
        "Nxy": 29,
        "F": 1.0,
        "F_value": "1.00"
    },
    "('V-IA', 'VII-IA')": {
        "Nx": 29,
        "Ny": 24,
        "Nxy": 11,
        "F": 0.41509433962264153,
        "F_value": "0.42"
    },
    "('V-IA', 'X-IA')": {
        "Nx": 29,
        "Ny": 19,
        "Nxy": 6,
        "F": 0.25,
        "F_value": "0.25"
    },
    "('V-IA', 'X-IC')": {
        "Nx": 29,
        "Ny": 18,
        "Nxy": 5,
        "F": 0.2127659574468085,
        "F_value": "0.21"
    },
    "('V-IA', 'X-IF')": {
        "Nx": 29,
        "Ny": 19,
        "Nxy": 7,
        "F": 0.2916666666666667,
        "F_value": "0.29"
    },
    "('V-IA', 'XII-IA')": {
        "Nx": 29,
        "Ny": 22,
        "Nxy": 5,
        "F": 0.19607843137254902,
        "F_value": "0.20"
    },
    "('V-IA', 'XII-IB')": {
        "Nx": 29,
        "Ny": 23,
        "Nxy": 5,
        "F": 0.19230769230769232,
        "F_value": "0.19"
    },
    "('V-IA', 'XIII-IA')": {
        "Nx": 29,
        "Ny": 29,
        "Nxy": 6,
        "F": 0.20689655172413793,
        "F_value": "0.21"
    },
    "('V-IA', 'XIV-IA')": {
        "Nx": 29,
        "Ny": 23,
        "Nxy": 5,
        "F": 0.19230769230769232,
        "F_value": "0.19"
    },
    "('V-IA', 'XIV-IC')": {
        "Nx": 29,
        "Ny": 23,
        "Nxy": 4,
        "F": 0.15384615384615385,
        "F_value": "0.15"
    },
    "('VII-IA', 'I-IA')": {
        "Nx": 24,
        "Ny": 23,
        "Nxy": 5,
        "F": 0.2127659574468085,
        "F_value": "0.21"
    },
    "('VII-IA', 'I-IB')": {
        "Nx": 24,
        "Ny": 25,
        "Nxy": 5,
        "F": 0.20408163265306123,
        "F_value": "0.20"
    },
    "('VII-IA', 'I-IC')": {
        "Nx": 24,
        "Ny": 23,
        "Nxy": 4,
        "F": 0.1702127659574468,
        "F_value": "0.17"
    },
    "('VII-IA', 'I-IE')": {
        "Nx": 24,
        "Ny": 25,
        "Nxy": 5,
        "F": 0.20408163265306123,
        "F_value": "0.20"
    },
    "('VII-IA', 'I-IF')": {
        "Nx": 24,
        "Ny": 24,
        "Nxy": 4,
        "F": 0.16666666666666666,
        "F_value": "0.17"
    },
    "('VII-IA', 'I-IIA')": {
        "Nx": 24,
        "Ny": 24,
        "Nxy": 6,
        "F": 0.25,
        "F_value": "0.25"
    },
    "('VII-IA', 'I-IIB')": {
        "Nx": 24,
        "Ny": 24,
        "Nxy": 5,
        "F": 0.20833333333333334,
        "F_value": "0.21"
    },
    "('VII-IA', 'I-IIIB')": {
        "Nx": 24,
        "Ny": 25,
        "Nxy": 5,
        "F": 0.20408163265306123,
        "F_value": "0.20"
    },
    "('VII-IA', 'I-IP')": {
        "Nx": 24,
        "Ny": 22,
        "Nxy": 5,
        "F": 0.21739130434782608,
        "F_value": "0.22"
    },
    "('VII-IA', 'I-IVB')": {
        "Nx": 24,
        "Ny": 25,
        "Nxy": 4,
        "F": 0.16326530612244897,
        "F_value": "0.16"
    },
    "('VII-IA', 'I-VB')": {
        "Nx": 24,
        "Ny": 24,
        "Nxy": 5,
        "F": 0.20833333333333334,
        "F_value": "0.21"
    },
    "('VII-IA', 'I-VIB')": {
        "Nx": 24,
        "Ny": 24,
        "Nxy": 5,
        "F": 0.20833333333333334,
        "F_value": "0.21"
    },
    "('VII-IA', 'II-IA')": {
        "Nx": 24,
        "Ny": 24,
        "Nxy": 2,
        "F": 0.08333333333333333,
        "F_value": "0.08"
    },
    "('VII-IA', 'IX-IB')": {
        "Nx": 24,
        "Ny": 22,
        "Nxy": 3,
        "F": 0.13043478260869565,
        "F_value": "0.13"
    },
    "('VII-IA', 'IX-IH')": {
        "Nx": 24,
        "Ny": 20,
        "Nxy": 8,
        "F": 0.36363636363636365,
        "F_value": "0.36"
    },
    "('VII-IA', 'V-IA')": {
        "Nx": 24,
        "Ny": 29,
        "Nxy": 11,
        "F": 0.41509433962264153,
        "F_value": "0.42"
    },
    "('VII-IA', 'VII-IA')": {
        "Nx": 24,
        "Ny": 24,
        "Nxy": 24,
        "F": 1.0,
        "F_value": "1.00"
    },
    "('VII-IA', 'X-IA')": {
        "Nx": 24,
        "Ny": 19,
        "Nxy": 5,
        "F": 0.23255813953488372,
        "F_value": "0.23"
    },
    "('VII-IA', 'X-IC')": {
        "Nx": 24,
        "Ny": 18,
        "Nxy": 5,
        "F": 0.23809523809523808,
        "F_value": "0.24"
    },
    "('VII-IA', 'X-IF')": {
        "Nx": 24,
        "Ny": 19,
        "Nxy": 7,
        "F": 0.32558139534883723,
        "F_value": "0.33"
    },
    "('VII-IA', 'XII-IA')": {
        "Nx": 24,
        "Ny": 22,
        "Nxy": 2,
        "F": 0.08695652173913043,
        "F_value": "0.09"
    },
    "('VII-IA', 'XII-IB')": {
        "Nx": 24,
        "Ny": 23,
        "Nxy": 3,
        "F": 0.1276595744680851,
        "F_value": "0.13"
    },
    "('VII-IA', 'XIII-IA')": {
        "Nx": 24,
        "Ny": 29,
        "Nxy": 5,
        "F": 0.18867924528301888,
        "F_value": "0.19"
    },
    "('VII-IA', 'XIV-IA')": {
        "Nx": 24,
        "Ny": 23,
        "Nxy": 4,
        "F": 0.1702127659574468,
        "F_value": "0.17"
    },
    "('VII-IA', 'XIV-IC')": {
        "Nx": 24,
        "Ny": 23,
        "Nxy": 4,
        "F": 0.1702127659574468,
        "F_value": "0.17"
    },
    "('X-IA', 'I-IA')": {
        "Nx": 19,
        "Ny": 23,
        "Nxy": 3,
        "F": 0.14285714285714285,
        "F_value": "0.14"
    },
    "('X-IA', 'I-IB')": {
        "Nx": 19,
        "Ny": 25,
        "Nxy": 3,
        "F": 0.13636363636363635,
        "F_value": "0.14"
    },
    "('X-IA', 'I-IC')": {
        "Nx": 19,
        "Ny": 23,
        "Nxy": 5,
        "F": 0.23809523809523808,
        "F_value": "0.24"
    },
    "('X-IA', 'I-IE')": {
        "Nx": 19,
        "Ny": 25,
        "Nxy": 5,
        "F": 0.22727272727272727,
        "F_value": "0.23"
    },
    "('X-IA', 'I-IF')": {
        "Nx": 19,
        "Ny": 24,
        "Nxy": 5,
        "F": 0.23255813953488372,
        "F_value": "0.23"
    },
    "('X-IA', 'I-IIA')": {
        "Nx": 19,
        "Ny": 24,
        "Nxy": 3,
        "F": 0.13953488372093023,
        "F_value": "0.14"
    },
    "('X-IA', 'I-IIB')": {
        "Nx": 19,
        "Ny": 24,
        "Nxy": 3,
        "F": 0.13953488372093023,
        "F_value": "0.14"
    },
    "('X-IA', 'I-IIIB')": {
        "Nx": 19,
        "Ny": 25,
        "Nxy": 3,
        "F": 0.13636363636363635,
        "F_value": "0.14"
    },
    "('X-IA', 'I-IP')": {
        "Nx": 19,
        "Ny": 22,
        "Nxy": 6,
        "F": 0.2926829268292683,
        "F_value": "0.29"
    },
    "('X-IA', 'I-IVB')": {
        "Nx": 19,
        "Ny": 25,
        "Nxy": 5,
        "F": 0.22727272727272727,
        "F_value": "0.23"
    },
    "('X-IA', 'I-VB')": {
        "Nx": 19,
        "Ny": 24,
        "Nxy": 3,
        "F": 0.13953488372093023,
        "F_value": "0.14"
    },
    "('X-IA', 'I-VIB')": {
        "Nx": 19,
        "Ny": 24,
        "Nxy": 3,
        "F": 0.13953488372093023,
        "F_value": "0.14"
    },
    "('X-IA', 'II-IA')": {
        "Nx": 19,
        "Ny": 24,
        "Nxy": 3,
        "F": 0.13953488372093023,
        "F_value": "0.14"
    },
    "('X-IA', 'IX-IB')": {
        "Nx": 19,
        "Ny": 22,
        "Nxy": 2,
        "F": 0.0975609756097561,
        "F_value": "0.10"
    },
    "('X-IA', 'IX-IH')": {
        "Nx": 19,
        "Ny": 20,
        "Nxy": 5,
        "F": 0.2564102564102564,
        "F_value": "0.26"
    },
    "('X-IA', 'V-IA')": {
        "Nx": 19,
        "Ny": 29,
        "Nxy": 6,
        "F": 0.25,
        "F_value": "0.25"
    },
    "('X-IA', 'VII-IA')": {
        "Nx": 19,
        "Ny": 24,
        "Nxy": 5,
        "F": 0.23255813953488372,
        "F_value": "0.23"
    },
    "('X-IA', 'X-IA')": {
        "Nx": 19,
        "Ny": 19,
        "Nxy": 19,
        "F": 1.0,
        "F_value": "1.00"
    },
    "('X-IA', 'X-IC')": {
        "Nx": 19,
        "Ny": 18,
        "Nxy": 12,
        "F": 0.6486486486486487,
        "F_value": "0.65"
    },
    "('X-IA', 'X-IF')": {
        "Nx": 19,
        "Ny": 19,
        "Nxy": 14,
        "F": 0.7368421052631579,
        "F_value": "0.74"
    },
    "('X-IA', 'XII-IA')": {
        "Nx": 19,
        "Ny": 22,
        "Nxy": 3,
        "F": 0.14634146341463414,
        "F_value": "0.15"
    },
    "('X-IA', 'XII-IB')": {
        "Nx": 19,
        "Ny": 23,
        "Nxy": 3,
        "F": 0.14285714285714285,
        "F_value": "0.14"
    },
    "('X-IA', 'XIII-IA')": {
        "Nx": 19,
        "Ny": 29,
        "Nxy": 7,
        "F": 0.2916666666666667,
        "F_value": "0.29"
    },
    "('X-IA', 'XIV-IA')": {
        "Nx": 19,
        "Ny": 23,
        "Nxy": 4,
        "F": 0.19047619047619047,
        "F_value": "0.19"
    },
    "('X-IA', 'XIV-IC')": {
        "Nx": 19,
        "Ny": 23,
        "Nxy": 3,
        "F": 0.14285714285714285,
        "F_value": "0.14"
    },
    "('X-IC', 'I-IA')": {
        "Nx": 18,
        "Ny": 23,
        "Nxy": 4,
        "F": 0.1951219512195122,
        "F_value": "0.20"
    },
    "('X-IC', 'I-IB')": {
        "Nx": 18,
        "Ny": 25,
        "Nxy": 4,
        "F": 0.18604651162790697,
        "F_value": "0.19"
    },
    "('X-IC', 'I-IC')": {
        "Nx": 18,
        "Ny": 23,
        "Nxy": 7,
        "F": 0.34146341463414637,
        "F_value": "0.34"
    },
    "('X-IC', 'I-IE')": {
        "Nx": 18,
        "Ny": 25,
        "Nxy": 6,
        "F": 0.27906976744186046,
        "F_value": "0.28"
    },
    "('X-IC', 'I-IF')": {
        "Nx": 18,
        "Ny": 24,
        "Nxy": 6,
        "F": 0.2857142857142857,
        "F_value": "0.29"
    },
    "('X-IC', 'I-IIA')": {
        "Nx": 18,
        "Ny": 24,
        "Nxy": 3,
        "F": 0.14285714285714285,
        "F_value": "0.14"
    },
    "('X-IC', 'I-IIB')": {
        "Nx": 18,
        "Ny": 24,
        "Nxy": 4,
        "F": 0.19047619047619047,
        "F_value": "0.19"
    },
    "('X-IC', 'I-IIIB')": {
        "Nx": 18,
        "Ny": 25,
        "Nxy": 4,
        "F": 0.18604651162790697,
        "F_value": "0.19"
    },
    "('X-IC', 'I-IP')": {
        "Nx": 18,
        "Ny": 22,
        "Nxy": 6,
        "F": 0.3,
        "F_value": "0.30"
    },
    "('X-IC', 'I-IVB')": {
        "Nx": 18,
        "Ny": 25,
        "Nxy": 6,
        "F": 0.27906976744186046,
        "F_value": "0.28"
    },
    "('X-IC', 'I-VB')": {
        "Nx": 18,
        "Ny": 24,
        "Nxy": 4,
        "F": 0.19047619047619047,
        "F_value": "0.19"
    },
    "('X-IC', 'I-VIB')": {
        "Nx": 18,
        "Ny": 24,
        "Nxy": 4,
        "F": 0.19047619047619047,
        "F_value": "0.19"
    },
    "('X-IC', 'II-IA')": {
        "Nx": 18,
        "Ny": 24,
        "Nxy": 3,
        "F": 0.14285714285714285,
        "F_value": "0.14"
    },
    "('X-IC', 'IX-IB')": {
        "Nx": 18,
        "Ny": 22,
        "Nxy": 4,
        "F": 0.2,
        "F_value": "0.20"
    },
    "('X-IC', 'IX-IH')": {
        "Nx": 18,
        "Ny": 20,
        "Nxy": 5,
        "F": 0.2631578947368421,
        "F_value": "0.26"
    },
    "('X-IC', 'V-IA')": {
        "Nx": 18,
        "Ny": 29,
        "Nxy": 5,
        "F": 0.2127659574468085,
        "F_value": "0.21"
    },
    "('X-IC', 'VII-IA')": {
        "Nx": 18,
        "Ny": 24,
        "Nxy": 5,
        "F": 0.23809523809523808,
        "F_value": "0.24"
    },
    "('X-IC', 'X-IA')": {
        "Nx": 18,
        "Ny": 19,
        "Nxy": 12,
        "F": 0.6486486486486487,
        "F_value": "0.65"
    },
    "('X-IC', 'X-IC')": {
        "Nx": 18,
        "Ny": 18,
        "Nxy": 18,
        "F": 1.0,
        "F_value": "1.00"
    },
    "('X-IC', 'X-IF')": {
        "Nx": 18,
        "Ny": 19,
        "Nxy": 12,
        "F": 0.6486486486486487,
        "F_value": "0.65"
    },
    "('X-IC', 'XII-IA')": {
        "Nx": 18,
        "Ny": 22,
        "Nxy": 3,
        "F": 0.15,
        "F_value": "0.15"
    },
    "('X-IC', 'XII-IB')": {
        "Nx": 18,
        "Ny": 23,
        "Nxy": 3,
        "F": 0.14634146341463414,
        "F_value": "0.15"
    },
    "('X-IC', 'XIII-IA')": {
        "Nx": 18,
        "Ny": 29,
        "Nxy": 6,
        "F": 0.2553191489361702,
        "F_value": "0.26"
    },
    "('X-IC', 'XIV-IA')": {
        "Nx": 18,
        "Ny": 23,
        "Nxy": 3,
        "F": 0.14634146341463414,
        "F_value": "0.15"
    },
    "('X-IC', 'XIV-IC')": {
        "Nx": 18,
        "Ny": 23,
        "Nxy": 3,
        "F": 0.14634146341463414,
        "F_value": "0.15"
    },
    "('X-IF', 'I-IA')": {
        "Nx": 19,
        "Ny": 23,
        "Nxy": 5,
        "F": 0.23809523809523808,
        "F_value": "0.24"
    },
    "('X-IF', 'I-IB')": {
        "Nx": 19,
        "Ny": 25,
        "Nxy": 5,
        "F": 0.22727272727272727,
        "F_value": "0.23"
    },
    "('X-IF', 'I-IC')": {
        "Nx": 19,
        "Ny": 23,
        "Nxy": 7,
        "F": 0.3333333333333333,
        "F_value": "0.33"
    },
    "('X-IF', 'I-IE')": {
        "Nx": 19,
        "Ny": 25,
        "Nxy": 7,
        "F": 0.3181818181818182,
        "F_value": "0.32"
    },
    "('X-IF', 'I-IF')": {
        "Nx": 19,
        "Ny": 24,
        "Nxy": 7,
        "F": 0.32558139534883723,
        "F_value": "0.33"
    },
    "('X-IF', 'I-IIA')": {
        "Nx": 19,
        "Ny": 24,
        "Nxy": 4,
        "F": 0.18604651162790697,
        "F_value": "0.19"
    },
    "('X-IF', 'I-IIB')": {
        "Nx": 19,
        "Ny": 24,
        "Nxy": 5,
        "F": 0.23255813953488372,
        "F_value": "0.23"
    },
    "('X-IF', 'I-IIIB')": {
        "Nx": 19,
        "Ny": 25,
        "Nxy": 5,
        "F": 0.22727272727272727,
        "F_value": "0.23"
    },
    "('X-IF', 'I-IP')": {
        "Nx": 19,
        "Ny": 22,
        "Nxy": 8,
        "F": 0.3902439024390244,
        "F_value": "0.39"
    },
    "('X-IF', 'I-IVB')": {
        "Nx": 19,
        "Ny": 25,
        "Nxy": 7,
        "F": 0.3181818181818182,
        "F_value": "0.32"
    },
    "('X-IF', 'I-VB')": {
        "Nx": 19,
        "Ny": 24,
        "Nxy": 5,
        "F": 0.23255813953488372,
        "F_value": "0.23"
    },
    "('X-IF', 'I-VIB')": {
        "Nx": 19,
        "Ny": 24,
        "Nxy": 5,
        "F": 0.23255813953488372,
        "F_value": "0.23"
    },
    "('X-IF', 'II-IA')": {
        "Nx": 19,
        "Ny": 24,
        "Nxy": 3,
        "F": 0.13953488372093023,
        "F_value": "0.14"
    },
    "('X-IF', 'IX-IB')": {
        "Nx": 19,
        "Ny": 22,
        "Nxy": 3,
        "F": 0.14634146341463414,
        "F_value": "0.15"
    },
    "('X-IF', 'IX-IH')": {
        "Nx": 19,
        "Ny": 20,
        "Nxy": 6,
        "F": 0.3076923076923077,
        "F_value": "0.31"
    },
    "('X-IF', 'V-IA')": {
        "Nx": 19,
        "Ny": 29,
        "Nxy": 7,
        "F": 0.2916666666666667,
        "F_value": "0.29"
    },
    "('X-IF', 'VII-IA')": {
        "Nx": 19,
        "Ny": 24,
        "Nxy": 7,
        "F": 0.32558139534883723,
        "F_value": "0.33"
    },
    "('X-IF', 'X-IA')": {
        "Nx": 19,
        "Ny": 19,
        "Nxy": 14,
        "F": 0.7368421052631579,
        "F_value": "0.74"
    },
    "('X-IF', 'X-IC')": {
        "Nx": 19,
        "Ny": 18,
        "Nxy": 12,
        "F": 0.6486486486486487,
        "F_value": "0.65"
    },
    "('X-IF', 'X-IF')": {
        "Nx": 19,
        "Ny": 19,
        "Nxy": 19,
        "F": 1.0,
        "F_value": "1.00"
    },
    "('X-IF', 'XII-IA')": {
        "Nx": 19,
        "Ny": 22,
        "Nxy": 4,
        "F": 0.1951219512195122,
        "F_value": "0.20"
    },
    "('X-IF', 'XII-IB')": {
        "Nx": 19,
        "Ny": 23,
        "Nxy": 4,
        "F": 0.19047619047619047,
        "F_value": "0.19"
    },
    "('X-IF', 'XIII-IA')": {
        "Nx": 19,
        "Ny": 29,
        "Nxy": 9,
        "F": 0.375,
        "F_value": "0.38"
    },
    "('X-IF', 'XIV-IA')": {
        "Nx": 19,
        "Ny": 23,
        "Nxy": 4,
        "F": 0.19047619047619047,
        "F_value": "0.19"
    },
    "('X-IF', 'XIV-IC')": {
        "Nx": 19,
        "Ny": 23,
        "Nxy": 3,
        "F": 0.14285714285714285,
        "F_value": "0.14"
    },
    "('XII-IA', 'I-IA')": {
        "Nx": 22,
        "Ny": 23,
        "Nxy": 3,
        "F": 0.13333333333333333,
        "F_value": "0.13"
    },
    "('XII-IA', 'I-IB')": {
        "Nx": 22,
        "Ny": 25,
        "Nxy": 3,
        "F": 0.1276595744680851,
        "F_value": "0.13"
    },
    "('XII-IA', 'I-IC')": {
        "Nx": 22,
        "Ny": 23,
        "Nxy": 3,
        "F": 0.13333333333333333,
        "F_value": "0.13"
    },
    "('XII-IA', 'I-IE')": {
        "Nx": 22,
        "Ny": 25,
        "Nxy": 3,
        "F": 0.1276595744680851,
        "F_value": "0.13"
    },
    "('XII-IA', 'I-IF')": {
        "Nx": 22,
        "Ny": 24,
        "Nxy": 3,
        "F": 0.13043478260869565,
        "F_value": "0.13"
    },
    "('XII-IA', 'I-IIA')": {
        "Nx": 22,
        "Ny": 24,
        "Nxy": 2,
        "F": 0.08695652173913043,
        "F_value": "0.09"
    },
    "('XII-IA', 'I-IIB')": {
        "Nx": 22,
        "Ny": 24,
        "Nxy": 3,
        "F": 0.13043478260869565,
        "F_value": "0.13"
    },
    "('XII-IA', 'I-IIIB')": {
        "Nx": 22,
        "Ny": 25,
        "Nxy": 3,
        "F": 0.1276595744680851,
        "F_value": "0.13"
    },
    "('XII-IA', 'I-IP')": {
        "Nx": 22,
        "Ny": 22,
        "Nxy": 3,
        "F": 0.13636363636363635,
        "F_value": "0.14"
    },
    "('XII-IA', 'I-IVB')": {
        "Nx": 22,
        "Ny": 25,
        "Nxy": 3,
        "F": 0.1276595744680851,
        "F_value": "0.13"
    },
    "('XII-IA', 'I-VB')": {
        "Nx": 22,
        "Ny": 24,
        "Nxy": 3,
        "F": 0.13043478260869565,
        "F_value": "0.13"
    },
    "('XII-IA', 'I-VIB')": {
        "Nx": 22,
        "Ny": 24,
        "Nxy": 3,
        "F": 0.13043478260869565,
        "F_value": "0.13"
    },
    "('XII-IA', 'II-IA')": {
        "Nx": 22,
        "Ny": 24,
        "Nxy": 2,
        "F": 0.08695652173913043,
        "F_value": "0.09"
    },
    "('XII-IA', 'IX-IB')": {
        "Nx": 22,
        "Ny": 22,
        "Nxy": 4,
        "F": 0.18181818181818182,
        "F_value": "0.18"
    },
    "('XII-IA', 'IX-IH')": {
        "Nx": 22,
        "Ny": 20,
        "Nxy": 4,
        "F": 0.19047619047619047,
        "F_value": "0.19"
    },
    "('XII-IA', 'V-IA')": {
        "Nx": 22,
        "Ny": 29,
        "Nxy": 5,
        "F": 0.19607843137254902,
        "F_value": "0.20"
    },
    "('XII-IA', 'VII-IA')": {
        "Nx": 22,
        "Ny": 24,
        "Nxy": 2,
        "F": 0.08695652173913043,
        "F_value": "0.09"
    },
    "('XII-IA', 'X-IA')": {
        "Nx": 22,
        "Ny": 19,
        "Nxy": 3,
        "F": 0.14634146341463414,
        "F_value": "0.15"
    },
    "('XII-IA', 'X-IC')": {
        "Nx": 22,
        "Ny": 18,
        "Nxy": 3,
        "F": 0.15,
        "F_value": "0.15"
    },
    "('XII-IA', 'X-IF')": {
        "Nx": 22,
        "Ny": 19,
        "Nxy": 4,
        "F": 0.1951219512195122,
        "F_value": "0.20"
    },
    "('XII-IA', 'XII-IA')": {
        "Nx": 22,
        "Ny": 22,
        "Nxy": 22,
        "F": 1.0,
        "F_value": "1.00"
    },
    "('XII-IA', 'XII-IB')": {
        "Nx": 22,
        "Ny": 23,
        "Nxy": 21,
        "F": 0.9333333333333333,
        "F_value": "0.93"
    },
    "('XII-IA', 'XIII-IA')": {
        "Nx": 22,
        "Ny": 29,
        "Nxy": 8,
        "F": 0.3137254901960784,
        "F_value": "0.31"
    },
    "('XII-IA', 'XIV-IA')": {
        "Nx": 22,
        "Ny": 23,
        "Nxy": 2,
        "F": 0.08888888888888889,
        "F_value": "0.09"
    },
    "('XII-IA', 'XIV-IC')": {
        "Nx": 22,
        "Ny": 23,
        "Nxy": 0,
        "F": 0.0,
        "F_value": "0.00"
    },
    "('XII-IB', 'I-IA')": {
        "Nx": 23,
        "Ny": 23,
        "Nxy": 3,
        "F": 0.13043478260869565,
        "F_value": "0.13"
    },
    "('XII-IB', 'I-IB')": {
        "Nx": 23,
        "Ny": 25,
        "Nxy": 3,
        "F": 0.125,
        "F_value": "0.12"
    },
    "('XII-IB', 'I-IC')": {
        "Nx": 23,
        "Ny": 23,
        "Nxy": 3,
        "F": 0.13043478260869565,
        "F_value": "0.13"
    },
    "('XII-IB', 'I-IE')": {
        "Nx": 23,
        "Ny": 25,
        "Nxy": 3,
        "F": 0.125,
        "F_value": "0.12"
    },
    "('XII-IB', 'I-IF')": {
        "Nx": 23,
        "Ny": 24,
        "Nxy": 3,
        "F": 0.1276595744680851,
        "F_value": "0.13"
    },
    "('XII-IB', 'I-IIA')": {
        "Nx": 23,
        "Ny": 24,
        "Nxy": 2,
        "F": 0.0851063829787234,
        "F_value": "0.09"
    },
    "('XII-IB', 'I-IIB')": {
        "Nx": 23,
        "Ny": 24,
        "Nxy": 3,
        "F": 0.1276595744680851,
        "F_value": "0.13"
    },
    "('XII-IB', 'I-IIIB')": {
        "Nx": 23,
        "Ny": 25,
        "Nxy": 3,
        "F": 0.125,
        "F_value": "0.12"
    },
    "('XII-IB', 'I-IP')": {
        "Nx": 23,
        "Ny": 22,
        "Nxy": 3,
        "F": 0.13333333333333333,
        "F_value": "0.13"
    },
    "('XII-IB', 'I-IVB')": {
        "Nx": 23,
        "Ny": 25,
        "Nxy": 3,
        "F": 0.125,
        "F_value": "0.12"
    },
    "('XII-IB', 'I-VB')": {
        "Nx": 23,
        "Ny": 24,
        "Nxy": 3,
        "F": 0.1276595744680851,
        "F_value": "0.13"
    },
    "('XII-IB', 'I-VIB')": {
        "Nx": 23,
        "Ny": 24,
        "Nxy": 3,
        "F": 0.1276595744680851,
        "F_value": "0.13"
    },
    "('XII-IB', 'II-IA')": {
        "Nx": 23,
        "Ny": 24,
        "Nxy": 2,
        "F": 0.0851063829787234,
        "F_value": "0.09"
    },
    "('XII-IB', 'IX-IB')": {
        "Nx": 23,
        "Ny": 22,
        "Nxy": 5,
        "F": 0.2222222222222222,
        "F_value": "0.22"
    },
    "('XII-IB', 'IX-IH')": {
        "Nx": 23,
        "Ny": 20,
        "Nxy": 4,
        "F": 0.18604651162790697,
        "F_value": "0.19"
    },
    "('XII-IB', 'V-IA')": {
        "Nx": 23,
        "Ny": 29,
        "Nxy": 5,
        "F": 0.19230769230769232,
        "F_value": "0.19"
    },
    "('XII-IB', 'VII-IA')": {
        "Nx": 23,
        "Ny": 24,
        "Nxy": 3,
        "F": 0.1276595744680851,
        "F_value": "0.13"
    },
    "('XII-IB', 'X-IA')": {
        "Nx": 23,
        "Ny": 19,
        "Nxy": 3,
        "F": 0.14285714285714285,
        "F_value": "0.14"
    },
    "('XII-IB', 'X-IC')": {
        "Nx": 23,
        "Ny": 18,
        "Nxy": 3,
        "F": 0.14634146341463414,
        "F_value": "0.15"
    },
    "('XII-IB', 'X-IF')": {
        "Nx": 23,
        "Ny": 19,
        "Nxy": 4,
        "F": 0.19047619047619047,
        "F_value": "0.19"
    },
    "('XII-IB', 'XII-IA')": {
        "Nx": 23,
        "Ny": 22,
        "Nxy": 21,
        "F": 0.9333333333333333,
        "F_value": "0.93"
    },
    "('XII-IB', 'XII-IB')": {
        "Nx": 23,
        "Ny": 23,
        "Nxy": 23,
        "F": 1.0,
        "F_value": "1.00"
    },
    "('XII-IB', 'XIII-IA')": {
        "Nx": 23,
        "Ny": 29,
        "Nxy": 7,
        "F": 0.2692307692307692,
        "F_value": "0.27"
    },
    "('XII-IB', 'XIV-IA')": {
        "Nx": 23,
        "Ny": 23,
        "Nxy": 2,
        "F": 0.08695652173913043,
        "F_value": "0.09"
    },
    "('XII-IB', 'XIV-IC')": {
        "Nx": 23,
        "Ny": 23,
        "Nxy": 0,
        "F": 0.0,
        "F_value": "0.00"
    },
    "('XIII-IA', 'I-IA')": {
        "Nx": 29,
        "Ny": 23,
        "Nxy": 6,
        "F": 0.23076923076923078,
        "F_value": "0.23"
    },
    "('XIII-IA', 'I-IB')": {
        "Nx": 29,
        "Ny": 25,
        "Nxy": 6,
        "F": 0.2222222222222222,
        "F_value": "0.22"
    },
    "('XIII-IA', 'I-IC')": {
        "Nx": 29,
        "Ny": 23,
        "Nxy": 7,
        "F": 0.2692307692307692,
        "F_value": "0.27"
    },
    "('XIII-IA', 'I-IE')": {
        "Nx": 29,
        "Ny": 25,
        "Nxy": 7,
        "F": 0.25925925925925924,
        "F_value": "0.26"
    },
    "('XIII-IA', 'I-IF')": {
        "Nx": 29,
        "Ny": 24,
        "Nxy": 7,
        "F": 0.2641509433962264,
        "F_value": "0.26"
    },
    "('XIII-IA', 'I-IIA')": {
        "Nx": 29,
        "Ny": 24,
        "Nxy": 5,
        "F": 0.18867924528301888,
        "F_value": "0.19"
    },
    "('XIII-IA', 'I-IIB')": {
        "Nx": 29,
        "Ny": 24,
        "Nxy": 6,
        "F": 0.22641509433962265,
        "F_value": "0.23"
    },
    "('XIII-IA', 'I-IIIB')": {
        "Nx": 29,
        "Ny": 25,
        "Nxy": 6,
        "F": 0.2222222222222222,
        "F_value": "0.22"
    },
    "('XIII-IA', 'I-IP')": {
        "Nx": 29,
        "Ny": 22,
        "Nxy": 7,
        "F": 0.27450980392156865,
        "F_value": "0.27"
    },
    "('XIII-IA', 'I-IVB')": {
        "Nx": 29,
        "Ny": 25,
        "Nxy": 7,
        "F": 0.25925925925925924,
        "F_value": "0.26"
    },
    "('XIII-IA', 'I-VB')": {
        "Nx": 29,
        "Ny": 24,
        "Nxy": 6,
        "F": 0.22641509433962265,
        "F_value": "0.23"
    },
    "('XIII-IA', 'I-VIB')": {
        "Nx": 29,
        "Ny": 24,
        "Nxy": 6,
        "F": 0.22641509433962265,
        "F_value": "0.23"
    },
    "('XIII-IA', 'II-IA')": {
        "Nx": 29,
        "Ny": 24,
        "Nxy": 2,
        "F": 0.07547169811320754,
        "F_value": "0.08"
    },
    "('XIII-IA', 'IX-IB')": {
        "Nx": 29,
        "Ny": 22,
        "Nxy": 2,
        "F": 0.0784313725490196,
        "F_value": "0.08"
    },
    "('XIII-IA', 'IX-IH')": {
        "Nx": 29,
        "Ny": 20,
        "Nxy": 6,
        "F": 0.24489795918367346,
        "F_value": "0.24"
    },
    "('XIII-IA', 'V-IA')": {
        "Nx": 29,
        "Ny": 29,
        "Nxy": 6,
        "F": 0.20689655172413793,
        "F_value": "0.21"
    },
    "('XIII-IA', 'VII-IA')": {
        "Nx": 29,
        "Ny": 24,
        "Nxy": 5,
        "F": 0.18867924528301888,
        "F_value": "0.19"
    },
    "('XIII-IA', 'X-IA')": {
        "Nx": 29,
        "Ny": 19,
        "Nxy": 7,
        "F": 0.2916666666666667,
        "F_value": "0.29"
    },
    "('XIII-IA', 'X-IC')": {
        "Nx": 29,
        "Ny": 18,
        "Nxy": 6,
        "F": 0.2553191489361702,
        "F_value": "0.26"
    },
    "('XIII-IA', 'X-IF')": {
        "Nx": 29,
        "Ny": 19,
        "Nxy": 9,
        "F": 0.375,
        "F_value": "0.38"
    },
    "('XIII-IA', 'XII-IA')": {
        "Nx": 29,
        "Ny": 22,
        "Nxy": 8,
        "F": 0.3137254901960784,
        "F_value": "0.31"
    },
    "('XIII-IA', 'XII-IB')": {
        "Nx": 29,
        "Ny": 23,
        "Nxy": 7,
        "F": 0.2692307692307692,
        "F_value": "0.27"
    },
    "('XIII-IA', 'XIII-IA')": {
        "Nx": 29,
        "Ny": 29,
        "Nxy": 29,
        "F": 1.0,
        "F_value": "1.00"
    },
    "('XIII-IA', 'XIV-IA')": {
        "Nx": 29,
        "Ny": 23,
        "Nxy": 4,
        "F": 0.15384615384615385,
        "F_value": "0.15"
    },
    "('XIII-IA', 'XIV-IC')": {
        "Nx": 29,
        "Ny": 23,
        "Nxy": 2,
        "F": 0.07692307692307693,
        "F_value": "0.08"
    },
    "('XIV-IA', 'I-IA')": {
        "Nx": 23,
        "Ny": 23,
        "Nxy": 0,
        "F": 0.0,
        "F_value": "0.00"
    },
    "('XIV-IA', 'I-IB')": {
        "Nx": 23,
        "Ny": 25,
        "Nxy": 0,
        "F": 0.0,
        "F_value": "0.00"
    },
    "('XIV-IA', 'I-IC')": {
        "Nx": 23,
        "Ny": 23,
        "Nxy": 1,
        "F": 0.043478260869565216,
        "F_value": "0.04"
    },
    "('XIV-IA', 'I-IE')": {
        "Nx": 23,
        "Ny": 25,
        "Nxy": 1,
        "F": 0.041666666666666664,
        "F_value": "0.04"
    },
    "('XIV-IA', 'I-IF')": {
        "Nx": 23,
        "Ny": 24,
        "Nxy": 1,
        "F": 0.0425531914893617,
        "F_value": "0.04"
    },
    "('XIV-IA', 'I-IIA')": {
        "Nx": 23,
        "Ny": 24,
        "Nxy": 0,
        "F": 0.0,
        "F_value": "0.00"
    },
    "('XIV-IA', 'I-IIB')": {
        "Nx": 23,
        "Ny": 24,
        "Nxy": 0,
        "F": 0.0,
        "F_value": "0.00"
    },
    "('XIV-IA', 'I-IIIB')": {
        "Nx": 23,
        "Ny": 25,
        "Nxy": 0,
        "F": 0.0,
        "F_value": "0.00"
    },
    "('XIV-IA', 'I-IP')": {
        "Nx": 23,
        "Ny": 22,
        "Nxy": 1,
        "F": 0.044444444444444446,
        "F_value": "0.04"
    },
    "('XIV-IA', 'I-IVB')": {
        "Nx": 23,
        "Ny": 25,
        "Nxy": 1,
        "F": 0.041666666666666664,
        "F_value": "0.04"
    },
    "('XIV-IA', 'I-VB')": {
        "Nx": 23,
        "Ny": 24,
        "Nxy": 0,
        "F": 0.0,
        "F_value": "0.00"
    },
    "('XIV-IA', 'I-VIB')": {
        "Nx": 23,
        "Ny": 24,
        "Nxy": 0,
        "F": 0.0,
        "F_value": "0.00"
    },
    "('XIV-IA', 'II-IA')": {
        "Nx": 23,
        "Ny": 24,
        "Nxy": 4,
        "F": 0.1702127659574468,
        "F_value": "0.17"
    },
    "('XIV-IA', 'IX-IB')": {
        "Nx": 23,
        "Ny": 22,
        "Nxy": 1,
        "F": 0.044444444444444446,
        "F_value": "0.04"
    },
    "('XIV-IA', 'IX-IH')": {
        "Nx": 23,
        "Ny": 20,
        "Nxy": 1,
        "F": 0.046511627906976744,
        "F_value": "0.05"
    },
    "('XIV-IA', 'V-IA')": {
        "Nx": 23,
        "Ny": 29,
        "Nxy": 5,
        "F": 0.19230769230769232,
        "F_value": "0.19"
    },
    "('XIV-IA', 'VII-IA')": {
        "Nx": 23,
        "Ny": 24,
        "Nxy": 4,
        "F": 0.1702127659574468,
        "F_value": "0.17"
    },
    "('XIV-IA', 'X-IA')": {
        "Nx": 23,
        "Ny": 19,
        "Nxy": 4,
        "F": 0.19047619047619047,
        "F_value": "0.19"
    },
    "('XIV-IA', 'X-IC')": {
        "Nx": 23,
        "Ny": 18,
        "Nxy": 3,
        "F": 0.14634146341463414,
        "F_value": "0.15"
    },
    "('XIV-IA', 'X-IF')": {
        "Nx": 23,
        "Ny": 19,
        "Nxy": 4,
        "F": 0.19047619047619047,
        "F_value": "0.19"
    },
    "('XIV-IA', 'XII-IA')": {
        "Nx": 23,
        "Ny": 22,
        "Nxy": 2,
        "F": 0.08888888888888889,
        "F_value": "0.09"
    },
    "('XIV-IA', 'XII-IB')": {
        "Nx": 23,
        "Ny": 23,
        "Nxy": 2,
        "F": 0.08695652173913043,
        "F_value": "0.09"
    },
    "('XIV-IA', 'XIII-IA')": {
        "Nx": 23,
        "Ny": 29,
        "Nxy": 4,
        "F": 0.15384615384615385,
        "F_value": "0.15"
    },
    "('XIV-IA', 'XIV-IA')": {
        "Nx": 23,
        "Ny": 23,
        "Nxy": 23,
        "F": 1.0,
        "F_value": "1.00"
    },
    "('XIV-IA', 'XIV-IC')": {
        "Nx": 23,
        "Ny": 23,
        "Nxy": 20,
        "F": 0.8695652173913043,
        "F_value": "0.87"
    },
    "('XIV-IC', 'I-IA')": {
        "Nx": 23,
        "Ny": 23,
        "Nxy": 0,
        "F": 0.0,
        "F_value": "0.00"
    },
    "('XIV-IC', 'I-IB')": {
        "Nx": 23,
        "Ny": 25,
        "Nxy": 0,
        "F": 0.0,
        "F_value": "0.00"
    },
    "('XIV-IC', 'I-IC')": {
        "Nx": 23,
        "Ny": 23,
        "Nxy": 1,
        "F": 0.043478260869565216,
        "F_value": "0.04"
    },
    "('XIV-IC', 'I-IE')": {
        "Nx": 23,
        "Ny": 25,
        "Nxy": 1,
        "F": 0.041666666666666664,
        "F_value": "0.04"
    },
    "('XIV-IC', 'I-IF')": {
        "Nx": 23,
        "Ny": 24,
        "Nxy": 1,
        "F": 0.0425531914893617,
        "F_value": "0.04"
    },
    "('XIV-IC', 'I-IIA')": {
        "Nx": 23,
        "Ny": 24,
        "Nxy": 0,
        "F": 0.0,
        "F_value": "0.00"
    },
    "('XIV-IC', 'I-IIB')": {
        "Nx": 23,
        "Ny": 24,
        "Nxy": 0,
        "F": 0.0,
        "F_value": "0.00"
    },
    "('XIV-IC', 'I-IIIB')": {
        "Nx": 23,
        "Ny": 25,
        "Nxy": 0,
        "F": 0.0,
        "F_value": "0.00"
    },
    "('XIV-IC', 'I-IP')": {
        "Nx": 23,
        "Ny": 22,
        "Nxy": 1,
        "F": 0.044444444444444446,
        "F_value": "0.04"
    },
    "('XIV-IC', 'I-IVB')": {
        "Nx": 23,
        "Ny": 25,
        "Nxy": 1,
        "F": 0.041666666666666664,
        "F_value": "0.04"
    },
    "('XIV-IC', 'I-VB')": {
        "Nx": 23,
        "Ny": 24,
        "Nxy": 0,
        "F": 0.0,
        "F_value": "0.00"
    },
    "('XIV-IC', 'I-VIB')": {
        "Nx": 23,
        "Ny": 24,
        "Nxy": 0,
        "F": 0.0,
        "F_value": "0.00"
    },
    "('XIV-IC', 'II-IA')": {
        "Nx": 23,
        "Ny": 24,
        "Nxy": 4,
        "F": 0.1702127659574468,
        "F_value": "0.17"
    },
    "('XIV-IC', 'IX-IB')": {
        "Nx": 23,
        "Ny": 22,
        "Nxy": 0,
        "F": 0.0,
        "F_value": "0.00"
    },
    "('XIV-IC', 'IX-IH')": {
        "Nx": 23,
        "Ny": 20,
        "Nxy": 1,
        "F": 0.046511627906976744,
        "F_value": "0.05"
    },
    "('XIV-IC', 'V-IA')": {
        "Nx": 23,
        "Ny": 29,
        "Nxy": 4,
        "F": 0.15384615384615385,
        "F_value": "0.15"
    },
    "('XIV-IC', 'VII-IA')": {
        "Nx": 23,
        "Ny": 24,
        "Nxy": 4,
        "F": 0.1702127659574468,
        "F_value": "0.17"
    },
    "('XIV-IC', 'X-IA')": {
        "Nx": 23,
        "Ny": 19,
        "Nxy": 3,
        "F": 0.14285714285714285,
        "F_value": "0.14"
    },
    "('XIV-IC', 'X-IC')": {
        "Nx": 23,
        "Ny": 18,
        "Nxy": 3,
        "F": 0.14634146341463414,
        "F_value": "0.15"
    },
    "('XIV-IC', 'X-IF')": {
        "Nx": 23,
        "Ny": 19,
        "Nxy": 3,
        "F": 0.14285714285714285,
        "F_value": "0.14"
    },
    "('XIV-IC', 'XII-IA')": {
        "Nx": 23,
        "Ny": 22,
        "Nxy": 0,
        "F": 0.0,
        "F_value": "0.00"
    },
    "('XIV-IC', 'XII-IB')": {
        "Nx": 23,
        "Ny": 23,
        "Nxy": 0,
        "F": 0.0,
        "F_value": "0.00"
    },
    "('XIV-IC', 'XIII-IA')": {
        "Nx": 23,
        "Ny": 29,
        "Nxy": 2,
        "F": 0.07692307692307693,
        "F_value": "0.08"
    },
    "('XIV-IC', 'XIV-IA')": {
        "Nx": 23,
        "Ny": 23,
        "Nxy": 20,
        "F": 0.8695652173913043,
        "F_value": "0.87"
    },
    "('XIV-IC', 'XIV-IC')": {
        "Nx": 23,
        "Ny": 23,
        "Nxy": 23,
        "F": 1.0,
        "F_value": "1.00"
    }
}